{
    "code": 200,
    "introduce": [
        {
            "name": "1.1、概述",
            "con": "DZ404是镍基沉淀硬化型定向凝固柱晶高温合金，是一种高强度抗氧化合金，使用温度在1050℃以下。合金不含铪及其他稀缺贵重元素，成本便宜且密度较低。合金具有良好的综合性能和可铸性。合金组织中无（γ+γ′）共晶相，初熔点高。主要产品是燃气涡轮发动机涡轮工作叶片和导向叶片及其他高温零件。"
        },
        {
            "name": "1.2、应用概况及特性",
            "con": "合金已用于制作航空发动机涡轮工作叶片和导向叶片。合金适用于制作在1000℃以下工作的燃气涡轮转子叶片和1050℃以下工作的导向叶片。@@合金铸造性能优异，可铸成壁厚小至0.5mm的带有复杂内腔的净成型定向凝固柱晶叶片、薄壁空心零件，不产生裂纹。"
        },
        {
            "name": "1.3、材料牌号",
            "con": "DZ404（DZ4）。"
        },
        {
            "name": "1.4、相近牌号",
            "con": "无。"
        },
        {
            "name": "1.5、材料技术标准",
            "con": "GB/T 14992 高温合金和金属间化合物高温材料的分类和牌号@@HB 7569 DZ4合金锭@@HB 7728 航空用高温合金涡轮工作精铸件规范@@HB 7762 航空发动机用定向凝固柱晶和单晶高温合金锭规范@@HB/Z 140 航空用高温合金热处理工艺@@Q/3B 475 DZ4合金定向凝固熔模铸造涡轮叶片"
        },
        {
            "name": "1.6、熔炼工艺",
            "con": "采用真空感应炉熔炼母合金，真空定向凝固炉浇注定向凝固铸件与试棒。"
        },
        {
            "name": "1.7、化学成分",
            "con": "摘自GB/T 14992，见表1-1。"
        },
        {
            "name": "1.8、热处理制度",
            "con": "摘自HB/Z 140，合金的标准热处理制度为：1220℃±10℃×4h/AC+870℃±10℃×32h/AC。"
        },
        {
            "name": "1.9、品种规格与供应状态",
            "con": "",
            "two": [
                {
                    "name": "1.9.1、品种规格与供应状态",
                    "con": "摘自HB 7569、HB 7762和Q/3B 475。"
                },
                {
                    "name": "1.9.2、主要规格",
                    "con": "母合金铸成圆形长棒，其直径范围为70mm～90mm。"
                },
                {
                    "name": "1.9.3、供应状态",
                    "con": "母合金以铸态供应，叶片铸件经热处理后供应。"
                }
            ]
        }
    ],
    "physicalChemistry": [
        {
            "name": "2.1、熔化温度范围",
            "con": "1310℃～1365℃（差热分析法）[1]。"
        },
        {
            "name": "2.2、相变点",
            "con": "无。"
        },
        {
            "name": "2.3、热导率",
            "con": "表2-1"
        },
        {
            "name": "2.4、电阻率",
            "con": "无。"
        },
        {
            "name": "2.5、热扩散率",
            "con": "表2-2"
        },
        {
            "name": "2.6、比热容",
            "con": "表2-3"
        },
        {
            "name": "2.7、线膨胀系数",
            "con": "表2-4"
        },
        {
            "name": "2.8、密度",
            "con": "ρ=(8.10～8.15)g/cm³[1]。"
        },
        {
            "name": "2.9、磁性能",
            "con": "合金无磁性。 "
        },
        {
            "name": "2.10、弹性性能",
            "con": "",
            "two": [
                {
                    "name": "2.10.1、合金的静弹性模量见表2-5；不同取向的动弹性模量见表2-6和图2-1。",
                    "con": ""
                },
                {
                    "name": "2.10.2、合金不同取向，不同温度的切变模量见表2-7和图2-2，泊松比见表2-8。",
                    "con": ""
                }
            ]
        },
        {
            "name": "2.11、抗氧化性能",
            "con": "合金在空气介质中，不同温度和试验时间的氧化速率见表2-9。"
        },
        {
            "name": "2.12、耐腐蚀性能",
            "con": "合金900℃、100h的腐蚀失重值见表2-10。"
        }
    ],
    "mechanical": [
        {
            "name": "3.1、供货技术标准",
            "con": "",
            "two": [
                {
                    "name": "3.1.1、技术标准规定的性能",
                    "con": "表3-1"
                },
                {
                    "name": "3.1.2、生产检验数据、基值和设计许用值",
                    "con": "无。"
                }
            ]
        },
        {
            "name": "3.2、硬度",
            "con": "合金经标准热处理，室温平均硬度为：HBS 356[1]。"
        },
        {
            "name": "3.3、冲击性能",
            "con": "无。"
        },
        {
            "name": "3.4、压缩性能",
            "con": "无。"
        },
        {
            "name": "3.5、扭转性能",
            "con": "无。"
        },
        {
            "name": "3.6、剪切性能",
            "con": "无。"
        },
        {
            "name": "3.7、拉伸性能",
            "con": "",
            "two": [
                {
                    "name": "3.7.1、合金不同温度典型的拉伸性能见表3-2和图3-1。",
                    "con": ""
                },
                {
                    "name": "3.7.2、合金经850℃和930℃长期时效，室温和760℃的拉伸性能见表3-3。",
                    "con": ""
                }
            ]
        },
        {
            "name": "3.8、持久性能",
            "con": "",
            "two": [
                {
                    "name": "3.8.1、合金不同温度和时间的持久极限见表3-4。几个合金不同温度100h的比持久强度见表3-5。 ",
                    "con": ""
                },
                {
                    "name": "3.8.2、合金不同温度的持久应力-寿命曲线见图3-2，持久热强参数综合曲线见图3-3。",
                    "con": ""
                },
                {
                    "name": "3.8.3、合金不同温度光滑和缺口持久性能见表3-6。",
                    "con": ""
                },
                {
                    "name": "3.8.4、叶片取样，不同温度的持久性能见表3-7。",
                    "con": ""
                }
            ]
        },
        {
            "name": "3.9、蠕变性能",
            "con": "合金不同温度和应力的蠕变曲线见图3-4～图3-6。"
        },
        {
            "name": "3.10、疲劳性能",
            "con": "",
            "two": [
                {
                    "name": "3.10.1、高周疲劳",
                    "con": "",
                    "third": [
                        {
                            "name": "3.10.1.1、合金700℃和930℃的旋转弯曲光滑疲劳极限见表3-8。",
                            "con": ""
                        },
                        {
                            "name": "3.10.1.2、合金900℃的旋转弯曲光滑和缺口疲劳S-N曲线（中值）见图3-7。",
                            "con": ""
                        },
                        {
                            "name": "3.10.1.3、航空涡轮实心和空心叶片，980℃的振动疲劳极限（中值）见表3-9，S-N曲线见图3-8。",
                            "con": ""
                        }
                    ]
                },
                {
                    "name": "3.10.2、低周疲劳",
                    "con": "",
                    "third": [
                        {
                            "name": "3.10.2.1、合金760℃的低周疲劳性能见表3-10，760℃的低周疲劳S-N曲线见图3-9。",
                            "con": ""
                        },
                        {
                            "name": "3.10.2.2、合金760℃的循环应力-应变曲线见图3-10。",
                            "con": ""
                        }
                    ]
                },
                {
                    "name": "3.10.3、特种疲劳",
                    "con": "",
                    "third": [
                        {
                            "name": "3.10.3.1、合金1000℃⇆20℃的冷热疲劳性能见表3-11。",
                            "con": ""
                        },
                        {
                            "name": "3.10.3.2、合金热机械疲劳试验结果见表3-12和图3-11。按照图3-11（TMF）曲线估算零件寿命，在涡轮叶片工作应力为196MPa时，估算零件寿命可达10000周次以上。",
                            "con": ""
                        },
                        {
                            "name": "3.10.3.3、合金不同温度的疲劳-蠕变交互作用性能见表3-13。850℃蠕变-疲劳交互作用下循环周次和相对蠕变量的关系曲线见图3-12。",
                            "con": ""
                        }
                    ]
                }
            ]
        },
        {
            "name": "3.11、裂纹扩展速率",
            "con": "合金室温应力比为0.1的疲劳裂纹dα/dN-△K曲线见图3-13。"
        },
        {
            "name": "3.12、断裂韧度",
            "con": "",
            "two": [
                {
                    "name": "3.12.1、几个合金的典型室温应力强度因子门槛值见表3-14。",
                    "con": ""
                },
                {
                    "name": "3.12.2、不同类型合金的室温断裂韧度对比结果见表3-15。",
                    "con": ""
                }
            ]
        },
        {
            "name": "3.13、松弛性能",
            "con": "无。"
        }
    ],
    "craft": [
        {
            "name": "4.1、成形工艺与性能",
            "con": "铸造性能优异，可成型薄壁空心零件，不产生裂纹。"
        },
        {
            "name": "4.2、工艺性能",
            "con": "无。"
        },
        {
            "name": "4.3、焊接性能",
            "con": "可以进行真空钎焊。"
        },
        {
            "name": "4.4、零件热处理工艺",
            "con": "无余量叶片热处理需在真空或保护气氛下进行：1220℃±10℃×4h/AC+870℃±10℃×32h/AC。"
        },
        {
            "name": "4.5、表面处理工艺",
            "con": "可采用料浆或气相渗Al，亦可用气相物理沉积或其他工艺涂层。"
        },
        {
            "name": "4.6、切削加工与磨削性能",
            "con": "无特殊要求。"
        }
    ],
    "microstructures": [
        {
            "name": "5.1、相变温度",
            "con": "无。"
        },
        {
            "name": "5.2、时间-温度-组织转变曲线",
            "con": "无。"
        },
        {
            "name": "5.3、典型组织",
            "con": "合金的铸态组织由γ基体、γ′相、MC型碳化物和极微量M3B2型硼化物组成，见图5-1。@@合金经标准热处理后，部分MC分解成M6C和M23C6型碳化物（图5-2），分布于柱晶界或在位错处沉淀析出，形成具有不同形态的复杂晶界，减少了MC的数量。经热处理后γ′相变小，排列整齐，呈立方体形，约占合金的61%（体积分数），虽然热处理后γ′相的分布趋于均匀，但在枝晶间的枝晶干的分布仍有区别，枝干均匀较细小，枝晶间较粗大且分布不均（图5-3）。"
        }
    ]
}