{
    "introduce": [
        {
            "name": "1.1、概述",
            "con": "GH2302是Fe-Ni-Cr基沉淀硬化型变形高温合金，铸造使用时合金牌号为K232。合金可在700℃以下长期使用，850℃短时使用。合金的组织与性能稳定，具有良好的冷热加工成形性能。主要产品有棒材、板材和精密铸件。"
        },
        {
            "name": "1.2、应用概况及特性",
            "con": "合金已用于制造涡轮喷气发动机加力燃烧室等，以及工业燃气轮机叶片等。合金在700℃和850℃无缺口敏感；在750℃×10000h时效后，晶内普遍析出竹叶状Laves4；该合金在固溶状态氩弧焊裂纹倾向性小，焊后再时效。板材进行接触焊较困难，应注意采用合适的焊接工艺。"
        },
        {
            "name": "1.3、材料牌号",
            "con": "GH2302(GH302、JF-43)，K232(K32)。"
        },
        {
            "name": "1.4、相近牌号",
            "con": "无"
        },
        {
            "name": "1.5、材料技术标准",
            "con": "GB/T  14992  高温合金和金属间化合物高温材料的分类和牌号@@GB/T14993    转动部件用高温合金热轧棒材@@GB/T  14995  高温合金热轧板@@GJB1952A      航空用高温合金冷轧薄板规范@@YB/T  5248  铸造高温合金母合金@@HB/Z140      航空用高温合金热处理工艺"
        },
        {
            "name": "1.6、熔炼与铸造工艺",
            "con": "",
            "two": [
                {
                    "name": "1.6.1、GH2302合金采用真空感应炉+电渣重熔、或真空感应炉+真空电弧重熔熔炼工艺。",
                    "con": ""
                },
                {
                    "name": "1.6.2、K232合金采用真空感应炉熔炼母合金，真空感应炉重熔浇注熔模精密铸造零件和试棒。",
                    "con": ""
                }
            ]
        },
        {
            "name": "1.7、化学成分",
            "con": "摘自GB/T14992,见表1-1。",
            "tableData": [
                {
                    "元素": "质量分数/%",
                    "C": "≤0.08",
                    "Cr": "12.00～16.00",
                    "Ni": "38.00～42.00",
                    "W": "3.50～4.50",
                    "Mo": "1.50～2.50",
                    "Al": "1.80～2.30",
                    "Ti": "2.30～2.80",
                    "Fe": "余",
                    "B": "≤0.010",
                    "Zr": "≤0.050",
                    "Ce": "≤0.020",
                    "Mn": "≤0.60",
                    "Si": "≤0.60",
                    "P": "≤0.020",
                    "S": "≤0.010"
                }
            ],
            "tableColumns": [
                {
                    "label": "元素",
                    "prop": "元素"
                },
                {
                    "label": "C",
                    "prop": "C"
                },
                {
                    "label": "Cr",
                    "prop": "Cr"
                },
                {
                    "label": "Ni",
                    "prop": "Ni"
                },
                {
                    "label": "W",
                    "prop": "W"
                },
                {
                    "label": "Mo",
                    "prop": "Mo"
                },
                {
                    "label": "Al",
                    "prop": "Al"
                },
                {
                    "label": "Ti",
                    "prop": "Ti"
                },
                {
                    "label": "Fe",
                    "prop": "Fe"
                },
                {
                    "label": "B",
                    "prop": "B"
                },
                {
                    "label": "Zr",
                    "prop": "Zr"
                },
                {
                    "label": "Ce",
                    "prop": "Ce"
                },
                {
                    "label": "Mn",
                    "prop": "Mn"
                },
                {
                    "label": "Si",
                    "prop": "Si"
                },
                {
                    "label": "P",
                    "prop": "P"
                },
                {
                    "label": "S",
                    "prop": "S"
                }
            ]
        },
        {
            "name": "1.8、热处理制度",
            "con": "摘自GB/T14993、GB/T14995、GJB1952A、HB/Z140和YB/T5248,各品种的标准热处理制度为：@@a)热轧棒材，1180℃±10℃×2h/AC+1050℃±10℃×4h/AC+800℃±10℃×16h/AC；b)热轧板材和冷轧薄板，(1100～1130)℃/AC+800℃±10℃×16h/AC；c)铸件，1100℃×(3～5)h/AC+800℃×16h/AC。"
        },
        {
            "name": "1.9、品种规格与供应状态",
            "con": "",
            "two": [
                {
                    "name": "1.9.1、品种规格与供应状态",
                    "con": "摘自GB/T14993、GB/T14995、GJB1952A和YB/T5248。"
                },
                {
                    "name": "1.9.2、主要规格",
                    "con": "d≤55mm热轧棒材；δ0.5mm～4mm冷轧薄板；δ4mm～14mm热轧中厚板；母合金铸成圆形长棒，其直径范围为75mm～90mm,长度不小于250mm。"
                },
                {
                    "name": "1.9.3、供应状态",
                    "con": "热轧棒材不经热处理供应；冷轧薄板和热轧中厚板经固溶处理后供应；母合金和铸件一般不经热处理供应。"
                }
            ]
        }
    ],
    "physicalChemistry": [
        {
            "name": "2.1、熔化温度范围",
            "con": "熔点为1375℃。"
        },
        {
            "name": "2.2、相变点",
            "con": "无"
        },
        {
            "name": "2.3、热导率",
            "con": "表2-1",
            "tableData": [
                {
                    "20": 10.47,
                    "100": 11.3,
                    "200": 12.14,
                    "300": 13.4,
                    "400": 14.65,
                    "500": 15.91,
                    "600": 17.58,
                    "700": 19.68,
                    "800": 22.19,
                    "900": 24.7,
                    "θ/℃": "λ/[W/(m·℃)]"
                }
            ],
            "tableColumns": [
                {
                    "label": "20",
                    "prop": "20"
                },
                {
                    "label": "100",
                    "prop": "100"
                },
                {
                    "label": "200",
                    "prop": "200"
                },
                {
                    "label": "300",
                    "prop": "300"
                },
                {
                    "label": "400",
                    "prop": "400"
                },
                {
                    "label": "500",
                    "prop": "500"
                },
                {
                    "label": "600",
                    "prop": "600"
                },
                {
                    "label": "700",
                    "prop": "700"
                },
                {
                    "label": "800",
                    "prop": "800"
                },
                {
                    "label": "900",
                    "prop": "900"
                },
                {
                    "label": "θ/℃",
                    "prop": "θ/℃"
                }
            ]
        },
        {
            "name": "2.4、电阻率",
            "con": "无"
        },
        {
            "name": "2.5、热扩散率",
            "con": "图2-1",
            "xAxisData": [],
            "echartMsg": {
                "echartId": "25",
                "xName": "",
                "yName": "",
                "minX": 12.14,
                "minY": 1.9348
            },
            "seriesData": [
                {
                    "name": "棒材-θ",
                    "type": "line",
                    "smooth": "smooth",
                    "data": [
                        [
                            "306.0492",
                            "4.3920"
                        ],
                        [
                            "408.9056",
                            "4.6271"
                        ],
                        [
                            "507.2694",
                            "5.1328"
                        ],
                        [
                            "605.6332",
                            "5.5886"
                        ],
                        [
                            "706.1250",
                            "6.0267"
                        ],
                        [
                            "806.8534",
                            "6.4291"
                        ],
                        [
                            "904.9807",
                            "6.7816"
                        ]
                    ]
                },
                {
                    "name": "板材-θ",
                    "type": "line",
                    "smooth": "smooth",
                    "data": [
                        [
                            "12.1400",
                            "2.4227"
                        ],
                        [
                            "112.6319",
                            "2.7254"
                        ],
                        [
                            "202.0106",
                            "3.1456"
                        ],
                        [
                            "299.1921",
                            "3.5338"
                        ],
                        [
                            "405.5953",
                            "3.9540"
                        ],
                        [
                            "509.3974",
                            "4.2246"
                        ],
                        [
                            "608.9435",
                            "4.4276"
                        ],
                        [
                            "706.1250",
                            "4.5950"
                        ],
                        [
                            "812.2917",
                            "4.6769"
                        ],
                        [
                            "909.4733",
                            "4.9298"
                        ]
                    ]
                },
                {
                    "name": "铸件-θ",
                    "type": "line",
                    "smooth": "smooth",
                    "data": [
                        [
                            "13.0859",
                            "1.9348"
                        ],
                        [
                            "106.0113",
                            "2.1876"
                        ],
                        [
                            "201.0648",
                            "2.4405"
                        ],
                        [
                            "302.7389",
                            "2.9960"
                        ],
                        [
                            "511.7620",
                            "3.4839"
                        ],
                        [
                            "406.5411",
                            "3.2133"
                        ],
                        [
                            "610.1258",
                            "3.5516"
                        ],
                        [
                            "712.7457",
                            "3.4839"
                        ],
                        [
                            "810.1637",
                            "3.5516"
                        ],
                        [
                            "909.4733",
                            "3.7012"
                        ]
                    ]
                }
            ]
        },
        {
            "name": "2.6、比热容",
            "con": "表2-2",
            "tableData": [
                {
                    "200": 440,
                    "300": 456,
                    "400": 461,
                    "500": 477,
                    "600": 515,
                    "700": 549,
                    "800": 595,
                    "900": 620,
                    "θ/℃": "c/[J/(kg·℃)]"
                }
            ],
            "tableColumns": [
                {
                    "label": "200",
                    "prop": "200"
                },
                {
                    "label": "300",
                    "prop": "300"
                },
                {
                    "label": "400",
                    "prop": "400"
                },
                {
                    "label": "500",
                    "prop": "500"
                },
                {
                    "label": "600",
                    "prop": "600"
                },
                {
                    "label": "700",
                    "prop": "700"
                },
                {
                    "label": "800",
                    "prop": "800"
                },
                {
                    "label": "900",
                    "prop": "900"
                },
                {
                    "label": "θ/℃",
                    "prop": "θ/℃"
                }
            ]
        },
        {
            "name": "2.7、线膨胀系数",
            "con": "表2-3",
            "tableData": [
                {
                    "θ/℃": "α/(10^(-6)℃^(-1))",
                    "20～100": 15.8,
                    "20～200": 15,
                    "20～300": 14.9,
                    "20～400": 15.2,
                    "20～500": 15.4,
                    "20～600": 15.6,
                    "20～700": 16,
                    "20～800": 16.3,
                    "20～900": 16.6
                }
            ],
            "tableColumns": [
                {
                    "label": "θ/℃",
                    "prop": "θ/℃"
                },
                {
                    "label": "20～100",
                    "prop": "20～100"
                },
                {
                    "label": "20～200",
                    "prop": "20～200"
                },
                {
                    "label": "20～300",
                    "prop": "20～300"
                },
                {
                    "label": "20～400",
                    "prop": "20～400"
                },
                {
                    "label": "20～500",
                    "prop": "20～500"
                },
                {
                    "label": "20～600",
                    "prop": "20～600"
                },
                {
                    "label": "20～700",
                    "prop": "20～700"
                },
                {
                    "label": "20～800",
                    "prop": "20～800"
                },
                {
                    "label": "20～900",
                    "prop": "20～900"
                }
            ]
        },
        {
            "name": "2.8、密度",
            "con": "ρ=8.09g/cm³"
        },
        {
            "name": "2.9、磁性能",
            "con": "无"
        },
        {
            "name": "2.10、弹性性能",
            "con": "表2-4",
            "tableData": [
                {
                    "20": 204,
                    "400": "—",
                    "500": "—",
                    "600": 167,
                    "700": 159,
                    "800": 153,
                    "900": 134,
                    "θ/℃": "ED/GPa_棒材"
                },
                {
                    "20": 195,
                    "400": 175,
                    "500": "—",
                    "600": 162,
                    "700": 155,
                    "800": 149,
                    "900": 136,
                    "θ/℃": "ED/GPa_板材"
                },
                {
                    "20": 77,
                    "400": 68,
                    "500": 65,
                    "600": 63,
                    "700": 60,
                    "800": 56,
                    "900": 52,
                    "θ/℃": "G/GPa"
                },
                {
                    "20": 0.27,
                    "400": 0.29,
                    "500": 0.3,
                    "600": 0.3,
                    "700": 0.3,
                    "800": 0.33,
                    "900": 0.35,
                    "θ/℃": "μ"
                }
            ],
            "tableColumns": [
                {
                    "label": "20",
                    "prop": "20"
                },
                {
                    "label": "400",
                    "prop": "400"
                },
                {
                    "label": "500",
                    "prop": "500"
                },
                {
                    "label": "600",
                    "prop": "600"
                },
                {
                    "label": "700",
                    "prop": "700"
                },
                {
                    "label": "800",
                    "prop": "800"
                },
                {
                    "label": "900",
                    "prop": "900"
                },
                {
                    "label": "θ/℃",
                    "prop": "θ/℃"
                }
            ]
        },
        {
            "name": "2.11、抗氧化性能",
            "con": "未渗Al和渗Al试样在空气介质中，不同温度试验100h的氧化速率见表2-5。",
            "tableData": [
                {
                    "800": 0.0541,
                    "900": 0.1169,
                    "1000": 0.4426,
                    "1100": 1.2066,
                    "θ/℃": "100h的氧化速率/ [g/(m²·h)]_基材"
                },
                {
                    "800": 0.0182,
                    "900": 0.0436,
                    "1000": 0.1736,
                    "1100": "—",
                    "θ/℃": "100h的氧化速率/ [g/(m²·h)]_渗Al"
                }
            ],
            "tableColumns": [
                {
                    "label": "800",
                    "prop": "800"
                },
                {
                    "label": "900",
                    "prop": "900"
                },
                {
                    "label": "1000",
                    "prop": "1000"
                },
                {
                    "label": "1100",
                    "prop": "1100"
                },
                {
                    "label": "θ/℃",
                    "prop": "θ/℃"
                }
            ]
        },
        {
            "name": "2.12、耐腐蚀性能",
            "con": "",
            "two": [
                {
                    "name": "2.12.1、合金经熔盐腐蚀，800℃不同时间的腐蚀增重值见图2-2。",
                    "con": "",
                    "xAxisData": [],
                    "echartMsg": {
                        "echartId": "2121",
                        "xName": "",
                        "yName": "",
                        "minX": 7.8192,
                        "minY": 0.4996
                    },
                    "seriesData": [
                        {
                            "name": "无保护层-t",
                            "type": "line",
                            "smooth": "smooth",
                            "data": [
                                [
                                    "14.3282",
                                    "27.7266"
                                ],
                                [
                                    "34.5214",
                                    "33.2930"
                                ],
                                [
                                    "54.7302",
                                    "38.8763"
                                ],
                                [
                                    "100.1844",
                                    "46.6795"
                                ]
                            ]
                        },
                        {
                            "name": "有保护层-t",
                            "type": "line",
                            "smooth": "smooth",
                            "data": [
                                [
                                    "7.8192",
                                    "0.6006"
                                ],
                                [
                                    "15.2735",
                                    "1.2396"
                                ],
                                [
                                    "35.2963",
                                    "1.6096"
                                ],
                                [
                                    "55.0711",
                                    "0.4996"
                                ],
                                [
                                    "74.5980",
                                    "0.8696"
                                ]
                            ]
                        }
                    ]
                },
                {
                    "name": "2.12.2、合金经盐膜腐蚀，800℃不同时间的腐蚀增重值见图2-3。",
                    "con": "",
                    "xAxisData": [],
                    "echartMsg": {
                        "echartId": "2122",
                        "xName": "",
                        "yName": "",
                        "minX": 3.148,
                        "minY": 0.3258
                    },
                    "seriesData": [
                        {
                            "name": "渗CrAl-t",
                            "type": "line",
                            "smooth": "smooth",
                            "data": [
                                [
                                    "92.8599",
                                    "1.3724"
                                ],
                                [
                                    "76.7891",
                                    "1.1306"
                                ],
                                [
                                    "83.9525",
                                    "1.3189"
                                ]
                            ]
                        },
                        {
                            "name": "基材-t",
                            "type": "line",
                            "smooth": "smooth",
                            "data": [
                                [
                                    "97.4168",
                                    "2.9220"
                                ],
                                [
                                    "92.5412",
                                    "2.6555"
                                ],
                                [
                                    "83.2212",
                                    "2.6437"
                                ],
                                [
                                    "75.9639",
                                    "2.6791"
                                ],
                                [
                                    "68.6130",
                                    "2.5667"
                                ],
                                [
                                    "6.5610",
                                    "0.7164"
                                ],
                                [
                                    "3.1480",
                                    "0.3258"
                                ]
                            ]
                        }
                    ]
                }
            ]
        },
        {
            "name": "2.13、衰减系数",
            "con": "GH2302合金和GH4037合金衰减系数对比见图2-4。",
            "xAxisData": [],
            "echartMsg": {
                "echartId": "213",
                "xName": "",
                "yName": "",
                "minX": 55.2009,
                "minY": 0.4311
            },
            "seriesData": [
                {
                    "name": "GH2302-σ",
                    "type": "line",
                    "smooth": "smooth",
                    "data": [
                        [
                            "55.5181",
                            "1.4247"
                        ],
                        [
                            "63.9665",
                            "1.1340"
                        ],
                        [
                            "72.4149",
                            "1.2849"
                        ],
                        [
                            "114.1665",
                            "1.6455"
                        ],
                        [
                            "128.0357",
                            "1.6482"
                        ],
                        [
                            "165.8082",
                            "1.2008"
                        ]
                    ]
                },
                {
                    "name": "GH4037-σ",
                    "type": "line",
                    "smooth": "smooth",
                    "data": [
                        [
                            "55.2009",
                            "0.4311"
                        ],
                        [
                            "85.7938",
                            "0.8932"
                        ],
                        [
                            "96.8084",
                            "0.8001"
                        ],
                        [
                            "112.8978",
                            "0.9221"
                        ],
                        [
                            "124.6909",
                            "1.0094"
                        ],
                        [
                            "141.4147",
                            "0.8028"
                        ],
                        [
                            "173.2763",
                            "0.4894"
                        ]
                    ]
                }
            ]
        }
    ],
    "mechanical": [
        {
            "name": "3.1、供货技术标准",
            "con": "",
            "two": [
                {
                    "name": "3.1.1、技术标准规定的性能（表3-1）",
                    "con": "",
                    "tableData": [
                        {
                            "拉伸性能_σb/MPa": "≥",
                            "拉伸性能_δ5/%": "≥",
                            "拉伸性能_ψ/%": "≥",
                            "持久性能_τ/h": "≥"
                        },
                        {
                            "标准号": "GB/T 14993",
                            "品种": "热轧棒",
                            "热处理": "标准热处理",
                            "θ/℃": 800,
                            "拉伸性能_σb/MPa": 665,
                            "拉伸性能_δ5/%": 4.5,
                            "拉伸性能_ψ/%": 8,
                            "持久性能_σ/MPa": -245,
                            "持久性能_τ/h": -100,
                            "室温硬度HBS": "—"
                        },
                        {
                            "标准号": "GB/T 14993",
                            "品种": "热轧棒",
                            "热处理": "标准热处理",
                            "θ/℃": 850,
                            "拉伸性能_σb/MPa": "—",
                            "拉伸性能_δ5/%": "—",
                            "拉伸性能_ψ/%": "—",
                            "持久性能_σ/MPa": 196,
                            "持久性能_τ/h": 50,
                            "室温硬度HBS": "341～269"
                        },
                        {
                            "标准号": "GB/T 14995",
                            "品种": "热轧板",
                            "热处理": "交货状态",
                            "θ/℃": 20,
                            "拉伸性能_σb/MPa": 685,
                            "拉伸性能_δ5/%": 30,
                            "拉伸性能_ψ/%": "实测",
                            "持久性能_σ/MPa": "—",
                            "持久性能_τ/h": "—",
                            "室温硬度HBS": "—"
                        },
                        {
                            "标准号": "GB/T 14995",
                            "品种": "热轧板",
                            "热处理": "标准热处理",
                            "θ/℃": 800,
                            "拉伸性能_σb/MPa": 540,
                            "拉伸性能_δ5/%": 6,
                            "拉伸性能_ψ/%": "实测",
                            "持久性能_σ/MPa": "—",
                            "持久性能_τ/h": "—",
                            "室温硬度HBS": "—"
                        },
                        {
                            "标准号": "GJB 1952①",
                            "品种": "冷轧薄板",
                            "热处理": "交货状态",
                            "θ/℃": 20,
                            "拉伸性能_σb/MPa": "≤1130",
                            "拉伸性能_δ5/%": 30,
                            "拉伸性能_ψ/%": "—",
                            "持久性能_σ/MPa": "—",
                            "持久性能_τ/h": "—",
                            "室温硬度HBS": "—"
                        },
                        {
                            "标准号": "GJB 1952①",
                            "品种": "冷轧薄板",
                            "热处理": "标准热处理",
                            "θ/℃": 800,
                            "拉伸性能_σb/MPa": 540,
                            "拉伸性能_δ5/%": 8,
                            "拉伸性能_ψ/%": "—",
                            "持久性能_σ/MPa": "I：275",
                            "持久性能_τ/h": 23,
                            "室温硬度HBS": "实测"
                        },
                        {
                            "标准号": "GJB 1952①",
                            "品种": "冷轧薄板",
                            "热处理": "标准热处理",
                            "θ/℃": 800,
                            "拉伸性能_σb/MPa": 540,
                            "拉伸性能_δ5/%": 8,
                            "拉伸性能_ψ/%": "—",
                            "持久性能_σ/MPa": "Ⅱ：215",
                            "持久性能_τ/h": 100,
                            "室温硬度HBS": "—"
                        },
                        {
                            "标准号": "YB/T 5248",
                            "品种": "母合金",
                            "热处理": "标准热处理",
                            "θ/℃": 20,
                            "拉伸性能_σb/MPa": 686,
                            "拉伸性能_δ5/%": 4,
                            "拉伸性能_ψ/%": 6,
                            "持久性能_σ/MPa": "—",
                            "持久性能_τ/h": "—",
                            "室温硬度HBS": "—"
                        },
                        {
                            "标准号": "YB/T 5248",
                            "品种": "母合金",
                            "热处理": "标准热处理",
                            "θ/℃": 750,
                            "拉伸性能_σb/MPa": "—",
                            "拉伸性能_δ5/%": "—",
                            "拉伸性能_ψ/%": "—",
                            "持久性能_σ/MPa": 392,
                            "持久性能_τ/h": 50,
                            "室温硬度HBS": "—"
                        },
                        {
                            "标准号": "①δ<1.5mm和>3.00mm板材的拉伸性能由双方协商，持久性能报实测结果；δ≥1.5mm~≤3.0mm板材的持久检验先按I组进行，不合格时再按Ⅱ组检验。"
                        }
                    ],
                    "tableColumns": [
                        {
                            "label": "拉伸性能_σb/MPa",
                            "prop": "拉伸性能_σb/MPa"
                        },
                        {
                            "label": "拉伸性能_δ5/%",
                            "prop": "拉伸性能_δ5/%"
                        },
                        {
                            "label": "拉伸性能_ψ/%",
                            "prop": "拉伸性能_ψ/%"
                        },
                        {
                            "label": "持久性能_τ/h",
                            "prop": "持久性能_τ/h"
                        }
                    ]
                },
                {
                    "name": "3.1.2、生产检验数据、基值和设计许用值（表3-2）",
                    "con": "",
                    "tableData": [
                        {
                            "拉伸性能_σP0.2/MPa": "A",
                            "拉伸性能_σP0.2/MPa_1": "B",
                            "拉伸性能_σP0.2/MPa_2": "S",
                            "拉伸性能_σb/MPa": "A",
                            "拉伸性能_σb/MPa_1": "B",
                            "拉伸性能_σb/MPa_2": "S",
                            "拉伸性能_δ5/%": "X̄",
                            "拉伸性能_δ5/%_1": "S",
                            "拉伸性能_ψ/%": "X̄",
                            "拉伸性能_ψ/%_1": "S"
                        },
                        {
                            "取样": "热轧棒",
                            "热处理": "标准热处理",
                            "θ/℃": 20,
                            "试样个数": 100,
                            "拉伸性能_σP0.2/MPa": 700,
                            "拉伸性能_σP0.2/MPa_1": 715,
                            "拉伸性能_σP0.2/MPa_2": "—",
                            "拉伸性能_σb/MPa": 1180,
                            "拉伸性能_σb/MPa_1": 1190,
                            "拉伸性能_σb/MPa_2": "—",
                            "拉伸性能_δ5/%": 20,
                            "拉伸性能_δ5/%_1": "—",
                            "拉伸性能_ψ/%": 22,
                            "拉伸性能_ψ/%_1": "—"
                        },
                        {
                            "取样": "热轧棒",
                            "热处理": "标准热处理",
                            "θ/℃": 700,
                            "试样个数": 100,
                            "拉伸性能_σP0.2/MPa": "—",
                            "拉伸性能_σP0.2/MPa_1": "—",
                            "拉伸性能_σP0.2/MPa_2": "—",
                            "拉伸性能_σb/MPa": 865,
                            "拉伸性能_σb/MPa_1": 905,
                            "拉伸性能_σb/MPa_2": "—",
                            "拉伸性能_δ5/%": 23,
                            "拉伸性能_δ5/%_1": "—",
                            "拉伸性能_ψ/%": 34,
                            "拉伸性能_ψ/%_1": "—"
                        },
                        {
                            "取样": "热轧棒",
                            "热处理": "标准热处理",
                            "θ/℃": 800,
                            "试样个数": 100,
                            "拉伸性能_σP0.2/MPa": "—",
                            "拉伸性能_σP0.2/MPa_1": "—",
                            "拉伸性能_σP0.2/MPa_2": "—",
                            "拉伸性能_σb/MPa": 680,
                            "拉伸性能_σb/MPa_1": 690,
                            "拉伸性能_σb/MPa_2": 665,
                            "拉伸性能_δ5/%": 20,
                            "拉伸性能_δ5/%_1": 4.5,
                            "拉伸性能_ψ/%": 28,
                            "拉伸性能_ψ/%_1": 8
                        },
                        {
                            "取样": "冷轧薄板",
                            "热处理": "交货状态",
                            "θ/℃": 20,
                            "试样个数": 100,
                            "拉伸性能_σP0.2/MPa": "—",
                            "拉伸性能_σP0.2/MPa_1": "—",
                            "拉伸性能_σP0.2/MPa_2": "—",
                            "拉伸性能_σb/MPa": 930,
                            "拉伸性能_σb/MPa_1": 990,
                            "拉伸性能_σb/MPa_2": "≤1130",
                            "拉伸性能_δ5/%": 37,
                            "拉伸性能_δ5/%_1": 30,
                            "拉伸性能_ψ/%": "—",
                            "拉伸性能_ψ/%_1": "—"
                        },
                        {
                            "取样": "冷轧薄板",
                            "热处理": "标准热处理",
                            "θ/℃": 800,
                            "试样个数": 100,
                            "拉伸性能_σP0.2/MPa": "—",
                            "拉伸性能_σP0.2/MPa_1": "—",
                            "拉伸性能_σP0.2/MPa_2": "—",
                            "拉伸性能_σb/MPa": 565,
                            "拉伸性能_σb/MPa_1": 605,
                            "拉伸性能_σb/MPa_2": 540,
                            "拉伸性能_δ5/%": 18,
                            "拉伸性能_δ5/%_1": 8,
                            "拉伸性能_ψ/%": "—",
                            "拉伸性能_ψ/%_1": "—"
                        },
                        {
                            "取样": "精铸试棒",
                            "热处理": "标准热处理",
                            "θ/℃": 20,
                            "试样个数": 100,
                            "拉伸性能_σP0.2/MPa": "—",
                            "拉伸性能_σP0.2/MPa_1": "—",
                            "拉伸性能_σP0.2/MPa_2": "—",
                            "拉伸性能_σb/MPa": 855,
                            "拉伸性能_σb/MPa_1": 890,
                            "拉伸性能_σb/MPa_2": 685,
                            "拉伸性能_δ5/%": 12,
                            "拉伸性能_δ5/%_1": 4,
                            "拉伸性能_ψ/%": 20,
                            "拉伸性能_ψ/%_1": 6
                        }
                    ],
                    "tableColumns": [
                        {
                            "label": "拉伸性能_σP0.2/MPa",
                            "prop": "拉伸性能_σP0.2/MPa"
                        },
                        {
                            "label": "拉伸性能_σP0.2/MPa_1",
                            "prop": "拉伸性能_σP0.2/MPa_1"
                        },
                        {
                            "label": "拉伸性能_σP0.2/MPa_2",
                            "prop": "拉伸性能_σP0.2/MPa_2"
                        },
                        {
                            "label": "拉伸性能_σb/MPa",
                            "prop": "拉伸性能_σb/MPa"
                        },
                        {
                            "label": "拉伸性能_σb/MPa_1",
                            "prop": "拉伸性能_σb/MPa_1"
                        },
                        {
                            "label": "拉伸性能_σb/MPa_2",
                            "prop": "拉伸性能_σb/MPa_2"
                        },
                        {
                            "label": "拉伸性能_δ5/%",
                            "prop": "拉伸性能_δ5/%"
                        },
                        {
                            "label": "拉伸性能_δ5/%_1",
                            "prop": "拉伸性能_δ5/%_1"
                        },
                        {
                            "label": "拉伸性能_ψ/%",
                            "prop": "拉伸性能_ψ/%"
                        },
                        {
                            "label": "拉伸性能_ψ/%_1",
                            "prop": "拉伸性能_ψ/%_1"
                        }
                    ]
                }
            ]
        },
        {
            "name": "3.2、硬度",
            "con": "",
            "two": [
                {
                    "name": "3.2.1、棒材经标准热处理，室温硬度为HBS300~293。",
                    "con": ""
                },
                {
                    "name": "3.2.2、板材经不同固溶处理，室温硬度见图3-1。",
                    "con": "",
                    "xAxisData": [],
                    "echartMsg": {
                        "echartId": "322",
                        "xName": "",
                        "yName": "",
                        "minX": 852.524,
                        "minY": 137.9112
                    },
                    "seriesData": [
                        {
                            "name": "固溶温度",
                            "type": "line",
                            "smooth": "smooth",
                            "data": [
                                [
                                    "852.5240",
                                    "418.0457"
                                ],
                                [
                                    "950.6550",
                                    "313.6818"
                                ],
                                [
                                    "995.8867",
                                    "216.8707"
                                ],
                                [
                                    "1143.4710",
                                    "162.5145"
                                ],
                                [
                                    "1192.0626",
                                    "137.9112"
                                ]
                            ]
                        }
                    ]
                }
            ]
        },
        {
            "name": "3.3、冲击性能",
            "con": "",
            "two": [
                {
                    "name": "3.3.1、不同产品，不同温度的冲击韧性见表3-3。",
                    "con": "",
                    "tableData": [
                        {
                            "取样/mm": "d22～32热轧棒 标准热处理",
                            "θ/℃": 20,
                            "αKU/(kJ/m²)": 475
                        },
                        {
                            "取样/mm": "d22～32热轧棒 标准热处理",
                            "θ/℃": 700,
                            "αKU/(kJ/m²)": 563
                        },
                        {
                            "取样/mm": "d22～32热轧棒 标准热处理",
                            "θ/℃": 800,
                            "αKU/(kJ/m²)": 475
                        },
                        {
                            "取样/mm": "d22～32热轧棒 标准热处理",
                            "θ/℃": 900,
                            "αKU/(kJ/m²)": 103
                        },
                        {
                            "取样/mm": "精铸试棒 标准热处理",
                            "θ/℃": 20,
                            "αKU/(kJ/m²)": 176
                        },
                        {
                            "取样/mm": "精铸试棒 标准热处理",
                            "θ/℃": 500,
                            "αKU/(kJ/m²)": 186
                        },
                        {
                            "取样/mm": "精铸试棒 标准热处理",
                            "θ/℃": 600,
                            "αKU/(kJ/m²)": 183
                        },
                        {
                            "取样/mm": "精铸试棒 标准热处理",
                            "θ/℃": 650,
                            "αKU/(kJ/m²)": 166
                        },
                        {
                            "取样/mm": "精铸试棒 标准热处理",
                            "θ/℃": 700,
                            "αKU/(kJ/m²)": 176
                        },
                        {
                            "取样/mm": "精铸试棒 标准热处理",
                            "θ/℃": 750,
                            "αKU/(kJ/m²)": 220
                        },
                        {
                            "取样/mm": "精铸试棒 标准热处理",
                            "θ/℃": 800,
                            "αKU/(kJ/m²)": 260
                        },
                        {
                            "取样/mm": "精铸试棒 标准热处理",
                            "θ/℃": 850,
                            "αKU/(kJ/m²)": 289
                        },
                        {
                            "取样/mm": "叶片铸件 标准热处理",
                            "θ/℃": 20,
                            "αKU/(kJ/m²)": 421
                        },
                        {
                            "取样/mm": "叶片铸件 标准热处理",
                            "θ/℃": 650,
                            "αKU/(kJ/m²)": 279
                        },
                        {
                            "取样/mm": "叶片铸件 标准热处理",
                            "θ/℃": 700,
                            "αKU/(kJ/m²)": 205
                        },
                        {
                            "取样/mm": "叶片铸件 标准热处理",
                            "θ/℃": 750,
                            "αKU/(kJ/m²)": 201
                        },
                        {
                            "取样/mm": "叶片铸件 标准热处理",
                            "θ/℃": 800,
                            "αKU/(kJ/m²)": 269
                        }
                    ],
                    "tableColumns": [
                        {
                            "label": "取样/mm",
                            "prop": "取样/mm"
                        },
                        {
                            "label": "θ/℃",
                            "prop": "θ/℃"
                        },
                        {
                            "label": "αKU/(kJ/m²)",
                            "prop": "αKU/(kJ/m²)"
                        }
                    ]
                },
                {
                    "name": "3.3.2、棒材经不同长期时效，室温和700℃的冲击韧性见表3-4。",
                    "con": "",
                    "tableData": [
                        {
                            "时效时间_t/h": 1000,
                            "700℃时效温度在20℃试验温度，αKU/(kJ/m²)": 245,
                            "700℃时效温度在700℃试验温度，αKU/(kJ/m²)": 431,
                            "700℃时效温度在20℃试验温度，αKU/(kJ/m²)_1": 156,
                            "700℃时效温度在700℃试验温度，αKU/(kJ/m²)_1": 284,
                            "700℃时效温度在20℃试验温度，αKU/(kJ/m²)_2": 98,
                            "700℃时效温度在700℃试验温度，αKU/(kJ/m²)_2": 245
                        },
                        {
                            "时效时间_t/h": 3000,
                            "700℃时效温度在20℃试验温度，αKU/(kJ/m²)": 181,
                            "700℃时效温度在700℃试验温度，αKU/(kJ/m²)": 373,
                            "700℃时效温度在20℃试验温度，αKU/(kJ/m²)_1": 98,
                            "700℃时效温度在700℃试验温度，αKU/(kJ/m²)_1": 196,
                            "700℃时效温度在20℃试验温度，αKU/(kJ/m²)_2": "—",
                            "700℃时效温度在700℃试验温度，αKU/(kJ/m²)_2": "—"
                        },
                        {
                            "时效时间_t/h": 4000,
                            "700℃时效温度在20℃试验温度，αKU/(kJ/m²)": "—",
                            "700℃时效温度在700℃试验温度，αKU/(kJ/m²)": "—",
                            "700℃时效温度在20℃试验温度，αKU/(kJ/m²)_1": 73,
                            "700℃时效温度在700℃试验温度，αKU/(kJ/m²)_1": "—",
                            "700℃时效温度在20℃试验温度，αKU/(kJ/m²)_2": "—",
                            "700℃时效温度在700℃试验温度，αKU/(kJ/m²)_2": "—"
                        },
                        {
                            "时效时间_t/h": 5000,
                            "700℃时效温度在20℃试验温度，αKU/(kJ/m²)": 124,
                            "700℃时效温度在700℃试验温度，αKU/(kJ/m²)": "—",
                            "700℃时效温度在20℃试验温度，αKU/(kJ/m²)_1": 54,
                            "700℃时效温度在700℃试验温度，αKU/(kJ/m²)_1": 157,
                            "700℃时效温度在20℃试验温度，αKU/(kJ/m²)_2": "—",
                            "700℃时效温度在700℃试验温度，αKU/(kJ/m²)_2": "—"
                        },
                        {
                            "时效时间_t/h": 7000,
                            "700℃时效温度在20℃试验温度，αKU/(kJ/m²)": "—",
                            "700℃时效温度在700℃试验温度，αKU/(kJ/m²)": "—",
                            "700℃时效温度在20℃试验温度，αKU/(kJ/m²)_1": 68,
                            "700℃时效温度在700℃试验温度，αKU/(kJ/m²)_1": 147,
                            "700℃时效温度在20℃试验温度，αKU/(kJ/m²)_2": "—",
                            "700℃时效温度在700℃试验温度，αKU/(kJ/m²)_2": "—"
                        },
                        {
                            "时效时间_t/h": 10000,
                            "700℃时效温度在20℃试验温度，αKU/(kJ/m²)": 69,
                            "700℃时效温度在700℃试验温度，αKU/(kJ/m²)": 275,
                            "700℃时效温度在20℃试验温度，αKU/(kJ/m²)_1": 78,
                            "700℃时效温度在700℃试验温度，αKU/(kJ/m²)_1": 157,
                            "700℃时效温度在20℃试验温度，αKU/(kJ/m²)_2": "—",
                            "700℃时效温度在700℃试验温度，αKU/(kJ/m²)_2": "—"
                        },
                        {
                            "时效时间_t/h": "注：棒材取样，经标准热处理。"
                        }
                    ],
                    "tableColumns": [
                        {
                            "label": "时效时间_t/h",
                            "prop": "时效时间_t/h"
                        },
                        {
                            "label": "700℃时效温度在20℃试验温度，αKU/(kJ/m²)",
                            "prop": "700℃时效温度在20℃试验温度，αKU/(kJ/m²)"
                        },
                        {
                            "label": "700℃时效温度在700℃试验温度，αKU/(kJ/m²)",
                            "prop": "700℃时效温度在700℃试验温度，αKU/(kJ/m²)"
                        },
                        {
                            "label": "700℃时效温度在20℃试验温度，αKU/(kJ/m²)_1",
                            "prop": "700℃时效温度在20℃试验温度，αKU/(kJ/m²)_1"
                        },
                        {
                            "label": "700℃时效温度在700℃试验温度，αKU/(kJ/m²)_1",
                            "prop": "700℃时效温度在700℃试验温度，αKU/(kJ/m²)_1"
                        },
                        {
                            "label": "700℃时效温度在20℃试验温度，αKU/(kJ/m²)_2",
                            "prop": "700℃时效温度在20℃试验温度，αKU/(kJ/m²)_2"
                        },
                        {
                            "label": "700℃时效温度在700℃试验温度，αKU/(kJ/m²)_2",
                            "prop": "700℃时效温度在700℃试验温度，αKU/(kJ/m²)_2"
                        }
                    ]
                }
            ]
        },
        {
            "name": "3.4、压缩性能",
            "con": "无"
        },
        {
            "name": "3.5、扭转性能",
            "con": "无"
        },
        {
            "name": "3.6、剪切性能",
            "con": "无"
        },
        {
            "name": "3.7、拉伸性能",
            "con": "",
            "two": [
                {
                    "name": "3.7.1、不同产品经不同冶炼工艺，不同温度的拉伸性能见表3-3。",
                    "con": "",
                    "tableData": [
                        {
                            "取样/mm": "d22～32热轧棒 标准热处理",
                            "θ/℃": 20,
                            "σP0.2/MPa": 749,
                            "σb/MPa": 1211,
                            "δ5/%": 20,
                            "ψ/%": 21
                        },
                        {
                            "取样/mm": "d22～32热轧棒 标准热处理",
                            "θ/℃": 600,
                            "σP0.2/MPa": 706,
                            "σb/MPa": 1115,
                            "δ5/%": 17,
                            "ψ/%": 21
                        },
                        {
                            "取样/mm": "d22～32热轧棒 标准热处理",
                            "θ/℃": 700,
                            "σP0.2/MPa": 781,
                            "σb/MPa": 1019,
                            "δ5/%": 22,
                            "ψ/%": 31
                        },
                        {
                            "取样/mm": "d22～32热轧棒 标准热处理",
                            "θ/℃": 750,
                            "σP0.2/MPa": "—",
                            "σb/MPa": "—",
                            "δ5/%": "—",
                            "ψ/%": "—"
                        },
                        {
                            "取样/mm": "d22～32热轧棒 标准热处理",
                            "θ/℃": 800,
                            "σP0.2/MPa": 613,
                            "σb/MPa": 744,
                            "δ5/%": 19,
                            "ψ/%": 28
                        },
                        {
                            "取样/mm": "d22～32热轧棒 标准热处理",
                            "θ/℃": 850,
                            "σP0.2/MPa": 411,
                            "σb/MPa": 647,
                            "δ5/%": 17,
                            "ψ/%": 28
                        },
                        {
                            "取样/mm": "d22～32热轧棒 标准热处理",
                            "θ/℃": 900,
                            "σP0.2/MPa": 289,
                            "σb/MPa": 414,
                            "δ5/%": 19,
                            "ψ/%": 34
                        },
                        {
                            "取样/mm": "δ0.8～4.0冷轧板 标准热处理",
                            "θ/℃": 20,
                            "σP0.2/MPa": 776,
                            "σb/MPa": 1264,
                            "δ5/%": 26,
                            "ψ/%": "—"
                        },
                        {
                            "取样/mm": "δ0.8～4.0冷轧板 标准热处理",
                            "θ/℃": 600,
                            "σP0.2/MPa": "—",
                            "σb/MPa": 1139,
                            "δ5/%": 25,
                            "ψ/%": "—"
                        },
                        {
                            "取样/mm": "δ0.8～4.0冷轧板 标准热处理",
                            "θ/℃": 700,
                            "σP0.2/MPa": 783,
                            "σb/MPa": 943,
                            "δ5/%": 12,
                            "ψ/%": "—"
                        },
                        {
                            "取样/mm": "δ0.8～4.0冷轧板 标准热处理",
                            "θ/℃": 750,
                            "σP0.2/MPa": 738,
                            "σb/MPa": 838,
                            "δ5/%": 8,
                            "ψ/%": "—"
                        },
                        {
                            "取样/mm": "δ0.8～4.0冷轧板 标准热处理",
                            "θ/℃": 800,
                            "σP0.2/MPa": 593,
                            "σb/MPa": 672,
                            "δ5/%": 7,
                            "ψ/%": "—"
                        },
                        {
                            "取样/mm": "δ0.8～4.0冷轧板 标准热处理",
                            "θ/℃": 850,
                            "σP0.2/MPa": 468,
                            "σb/MPa": 474,
                            "δ5/%": 19,
                            "ψ/%": "—"
                        },
                        {
                            "取样/mm": "δ0.8～4.0冷轧板 标准热处理",
                            "θ/℃": 900,
                            "σP0.2/MPa": "—",
                            "σb/MPa": 318,
                            "δ5/%": 26,
                            "ψ/%": "—"
                        }
                    ],
                    "tableColumns": [
                        {
                            "label": "取样/mm",
                            "prop": "取样/mm"
                        },
                        {
                            "label": "θ/℃",
                            "prop": "θ/℃"
                        },
                        {
                            "label": "σP0.2/MPa",
                            "prop": "σP0.2/MPa"
                        },
                        {
                            "label": "σb/MPa",
                            "prop": "σb/MPa"
                        },
                        {
                            "label": "δ5/%",
                            "prop": "δ5/%"
                        },
                        {
                            "label": "ψ/%",
                            "prop": "ψ/%"
                        }
                    ]
                },
                {
                    "name": "3.7.2、板材经不同冷轧压下量，室温拉伸性能曲线见图3-5。",
                    "con": ""
                },
                {
                    "name": "3.7.3、板材经不同固溶处理，不同温度的拉伸性能曲线见图3-6。",
                    "con": ""
                },
                {
                    "name": "3.7.4、板材经不同长期时效，再经1150℃恢复热处理后的室温拉伸性能见表3-4;不同温度的拉伸性能见表3-5。",
                    "con": ""
                },
                {
                    "name": "3.7.5、棒材和冷轧板不同温度的拉伸性能见表3-5。",
                    "con": ""
                },
                {
                    "name": "3.7.6、棒材和板材经长期时效，不同温度的拉伸性能分别见表3-6和表3-7。",
                    "con": ""
                },
                {
                    "name": "3.7.6_2、棒材和板材经长期时效，不同温度的拉伸性能分别见表3-6和表3-7。",
                    "con": ""
                }
            ]
        },
        {
            "name": "3.8、持久性能",
            "con": "",
            "two": [
                {
                    "name": "3.8.1、棒材和板材不同温度和时间的持久强度见表3-8。",
                    "con": "",
                    "tableData": [
                        {
                            "取样": "棒材 标准热处理",
                            "θ/℃": 650,
                            "σt/h/MPa_σ100": 726,
                            "σt/h/MPa_σ500": 627,
                            "σt/h/MPa_σ1000": 570,
                            "σt/h/MPa_σ10000": 460,
                            "σt/h/MPa_σ100000": "—"
                        },
                        {
                            "取样": "棒材 标准热处理",
                            "θ/℃": 700,
                            "σt/h/MPa_σ100": 588,
                            "σt/h/MPa_σ500": 490,
                            "σt/h/MPa_σ1000": 412,
                            "σt/h/MPa_σ10000": 314,
                            "σt/h/MPa_σ100000": 226
                        },
                        {
                            "取样": "棒材 标准热处理",
                            "θ/℃": 750,
                            "σt/h/MPa_σ100": 441,
                            "σt/h/MPa_σ500": 353,
                            "σt/h/MPa_σ1000": 294,
                            "σt/h/MPa_σ10000": 196,
                            "σt/h/MPa_σ100000": "—"
                        },
                        {
                            "取样": "棒材 标准热处理",
                            "θ/℃": 800,
                            "σt/h/MPa_σ100": 304,
                            "σt/h/MPa_σ500": 235,
                            "σt/h/MPa_σ1000": 196,
                            "σt/h/MPa_σ10000": 130,
                            "σt/h/MPa_σ100000": "—"
                        },
                        {
                            "取样": "棒材 标准热处理",
                            "θ/℃": 850,
                            "σt/h/MPa_σ100": 225,
                            "σt/h/MPa_σ500": "—",
                            "σt/h/MPa_σ1000": "—",
                            "σt/h/MPa_σ10000": "—",
                            "σt/h/MPa_σ100000": "—"
                        },
                        {
                            "取样": "棒材 标准热处理",
                            "θ/℃": 900,
                            "σt/h/MPa_σ100": 118,
                            "σt/h/MPa_σ500": "—",
                            "σt/h/MPa_σ1000": "—",
                            "σt/h/MPa_σ10000": "—",
                            "σt/h/MPa_σ100000": "—"
                        },
                        {
                            "取样": "板材 标准热处理",
                            "θ/℃": 650,
                            "σt/h/MPa_σ100": "—",
                            "σt/h/MPa_σ500": "—",
                            "σt/h/MPa_σ1000": "—",
                            "σt/h/MPa_σ10000": "—",
                            "σt/h/MPa_σ100000": "—"
                        },
                        {
                            "取样": "板材 标准热处理",
                            "θ/℃": 700,
                            "σt/h/MPa_σ100": 500,
                            "σt/h/MPa_σ500": 402,
                            "σt/h/MPa_σ1000": 360,
                            "σt/h/MPa_σ10000": "—",
                            "σt/h/MPa_σ100000": "—"
                        },
                        {
                            "取样": "板材 标准热处理",
                            "θ/℃": 750,
                            "σt/h/MPa_σ100": 353,
                            "σt/h/MPa_σ500": 300,
                            "σt/h/MPa_σ1000": 260,
                            "σt/h/MPa_σ10000": "—",
                            "σt/h/MPa_σ100000": "—"
                        },
                        {
                            "取样": "板材 标准热处理",
                            "θ/℃": 800,
                            "σt/h/MPa_σ100": 245,
                            "σt/h/MPa_σ500": 196,
                            "σt/h/MPa_σ1000": 167,
                            "σt/h/MPa_σ10000": "—",
                            "σt/h/MPa_σ100000": "—"
                        },
                        {
                            "取样": "板材 标准热处理",
                            "θ/℃": 850,
                            "σt/h/MPa_σ100": 160,
                            "σt/h/MPa_σ500": 100,
                            "σt/h/MPa_σ1000": 85,
                            "σt/h/MPa_σ10000": "—",
                            "σt/h/MPa_σ100000": "—"
                        },
                        {
                            "取样": "板材 标准热处理",
                            "θ/℃": 900,
                            "σt/h/MPa_σ100": 78,
                            "σt/h/MPa_σ500": 54,
                            "σt/h/MPa_σ1000": "—",
                            "σt/h/MPa_σ10000": "—",
                            "σt/h/MPa_σ100000": "—"
                        },
                        {
                            "取样": "注：根据持久应力-寿命曲线和持久热强参数综合曲线，并参照试验数据确定。"
                        }
                    ],
                    "tableColumns": [
                        {
                            "label": "取样",
                            "prop": "取样"
                        },
                        {
                            "label": "θ/℃",
                            "prop": "θ/℃"
                        },
                        {
                            "label": "σt/h/MPa_σ100",
                            "prop": "σt/h/MPa_σ100"
                        },
                        {
                            "label": "σt/h/MPa_σ500",
                            "prop": "σt/h/MPa_σ500"
                        },
                        {
                            "label": "σt/h/MPa_σ1000",
                            "prop": "σt/h/MPa_σ1000"
                        },
                        {
                            "label": "σt/h/MPa_σ10000",
                            "prop": "σt/h/MPa_σ10000"
                        },
                        {
                            "label": "σt/h/MPa_σ100000",
                            "prop": "σt/h/MPa_σ100000"
                        }
                    ]
                },
                {
                    "name": "3.8.2、棒材不同温度的持久应力-寿命曲线见图3-2；圆饼不同温度的持久应力-寿命曲线见图3-3。",
                    "con": "",
                    "xAxisData": [],
                    "echartMsg": {
                        "echartId": "382",
                        "xName": "",
                        "yName": "",
                        "minX": 160.6178,
                        "minY": 226.4085
                    },
                    "seriesData": [
                        {
                            "name": "650℃-t",
                            "type": "line",
                            "smooth": "smooth",
                            "data": [
                                [
                                    "160.6178",
                                    "655.4625"
                                ],
                                [
                                    "268.1044",
                                    "625.8090"
                                ],
                                [
                                    "449.9002",
                                    "628.0707"
                                ]
                            ]
                        },
                        {
                            "name": "700℃-t",
                            "type": "line",
                            "smooth": "smooth",
                            "data": [
                                [
                                    "295.7249",
                                    "465.5563"
                                ],
                                [
                                    "1739.6692",
                                    "431.3307"
                                ],
                                [
                                    "10896.4185",
                                    "324.1752"
                                ]
                            ]
                        },
                        {
                            "name": "750℃-t",
                            "type": "line",
                            "smooth": "smooth",
                            "data": [
                                [
                                    "181.4412",
                                    "384.0739"
                                ],
                                [
                                    "1375.3677",
                                    "297.2890"
                                ],
                                [
                                    "4504.4866",
                                    "250.1718"
                                ],
                                [
                                    "5504.6693",
                                    "226.4085"
                                ]
                            ]
                        }
                    ]
                },
                {
                    "name": "3.8.22、棒材不同温度的持久应力-寿命曲线见图3-2；圆饼不同温度的持久应力-寿命曲线见图3-3。",
                    "con": ""
                },
                {
                    "name": "3.8.3、棒材和板材的持久热强参数综合曲线见图3-4。",
                    "con": ""
                },
                {
                    "name": "3.8.4、薄板不同温度的持久性能见表3-9；经800℃和850℃长期时效，不同试验条件的持久性能见表3-10。",
                    "con": ""
                },
                {
                    "name": "3.8.4_2、薄板不同温度的持久性能见表3-9；经800℃和850℃长期时效，不同试验条件的持久性能见表3-10。",
                    "con": ""
                }
            ]
        },
        {
            "name": "3.9、蠕变性能",
            "con": "",
            "two": [
                {
                    "name": "3.9.1、棒材和板材不同温度、100h的蠕变性能见表3-11。",
                    "con": "",
                    "tableData": [
                        {
                            "冶炼工艺": "真空感应炉+真空自耗",
                            "取样/mm": "d22～32棒材 标准热处理",
                            "θ/℃": 700,
                            "σ/MPa": 392,
                            "100h的蠕变性能_εt/%": 0.306,
                            "100h的蠕变性能_εP/%": 0.033
                        },
                        {
                            "冶炼工艺": "真空感应炉+真空自耗",
                            "取样/mm": "d22～32棒材 标准热处理",
                            "θ/℃": 800,
                            "σ/MPa": 225,
                            "100h的蠕变性能_εt/%": 0.227,
                            "100h的蠕变性能_εP/%": 0.077
                        },
                        {
                            "冶炼工艺": "真空感应炉+真空自耗",
                            "取样/mm": "d22～32棒材 标准热处理",
                            "θ/℃": 850,
                            "σ/MPa": 176,
                            "100h的蠕变性能_εt/%": 0.274,
                            "100h的蠕变性能_εP/%": 0.093
                        },
                        {
                            "冶炼工艺": "真空感应炉+电渣",
                            "取样/mm": "δ0.8～4冷轧板 标准热处理",
                            "θ/℃": 750,
                            "σ/MPa": 225,
                            "100h的蠕变性能_εt/%": 0.3,
                            "100h的蠕变性能_εP/%": 0.154
                        },
                        {
                            "冶炼工艺": "真空感应炉+电渣",
                            "取样/mm": "δ0.8～4冷轧板 标准热处理",
                            "θ/℃": 800,
                            "σ/MPa": 147,
                            "100h的蠕变性能_εt/%": 0.336,
                            "100h的蠕变性能_εP/%": 0.227
                        }
                    ],
                    "tableColumns": [
                        {
                            "label": "冶炼工艺",
                            "prop": "冶炼工艺"
                        },
                        {
                            "label": "取样/mm",
                            "prop": "取样/mm"
                        },
                        {
                            "label": "θ/℃",
                            "prop": "θ/℃"
                        },
                        {
                            "label": "σ/MPa",
                            "prop": "σ/MPa"
                        },
                        {
                            "label": "100h的蠕变性能_εt/%",
                            "prop": "100h的蠕变性能_εt/%"
                        },
                        {
                            "label": "100h的蠕变性能_εP/%",
                            "prop": "100h的蠕变性能_εP/%"
                        }
                    ]
                },
                {
                    "name": "3.9.2、棒材800℃和850℃的蠕变曲线见图3-5。",
                    "con": "",
                    "xAxisData": [],
                    "echartMsg": {
                        "echartId": "392",
                        "xName": "",
                        "yName": "",
                        "minX": 0.7269,
                        "minY": 0.1524
                    },
                    "seriesData": [
                        {
                            "name": "800℃、225MPa-t",
                            "type": "line",
                            "smooth": "smooth",
                            "data": [
                                [
                                    "97.6877",
                                    "0.2445"
                                ],
                                [
                                    "93.8951",
                                    "0.2445"
                                ],
                                [
                                    "90.1025",
                                    "0.2406"
                                ],
                                [
                                    "86.3098",
                                    "0.2406"
                                ],
                                [
                                    "82.5172",
                                    "0.2367"
                                ],
                                [
                                    "78.7245",
                                    "0.2367"
                                ],
                                [
                                    "74.9319",
                                    "0.2329"
                                ],
                                [
                                    "71.1393",
                                    "0.2290"
                                ],
                                [
                                    "67.3466",
                                    "0.2290"
                                ],
                                [
                                    "63.5540",
                                    "0.2251"
                                ],
                                [
                                    "59.7614",
                                    "0.2251"
                                ],
                                [
                                    "55.9687",
                                    "0.2213"
                                ],
                                [
                                    "52.1761",
                                    "0.2213"
                                ],
                                [
                                    "41.1775",
                                    "0.2136"
                                ],
                                [
                                    "37.3848",
                                    "0.2097"
                                ],
                                [
                                    "33.5922",
                                    "0.2097"
                                ],
                                [
                                    "50.6591",
                                    "0.2213"
                                ],
                                [
                                    "46.8664",
                                    "0.2174"
                                ],
                                [
                                    "43.0738",
                                    "0.2136"
                                ],
                                [
                                    "30.1694",
                                    "0.2098"
                                ],
                                [
                                    "27.0559",
                                    "0.2041"
                                ],
                                [
                                    "23.3573",
                                    "0.2028"
                                ],
                                [
                                    "20.3483",
                                    "0.2017"
                                ],
                                [
                                    "17.2347",
                                    "0.2017"
                                ],
                                [
                                    "4.4255",
                                    "0.1864"
                                ],
                                [
                                    "7.3091",
                                    "0.1934"
                                ],
                                [
                                    "9.9629",
                                    "0.1981"
                                ],
                                [
                                    "12.0525",
                                    "0.1971"
                                ],
                                [
                                    "14.7063",
                                    "0.1981"
                                ]
                            ]
                        },
                        {
                            "name": "850℃、176MPa-t",
                            "type": "line",
                            "smooth": "smooth",
                            "data": [
                                [
                                    "90.8610",
                                    "0.3834"
                                ],
                                [
                                    "88.2061",
                                    "0.3641"
                                ],
                                [
                                    "84.7928",
                                    "0.3448"
                                ],
                                [
                                    "81.0001",
                                    "0.3255"
                                ],
                                [
                                    "77.5867",
                                    "0.3101"
                                ],
                                [
                                    "74.1734",
                                    "0.2946"
                                ],
                                [
                                    "70.3808",
                                    "0.2831"
                                ],
                                [
                                    "66.9674",
                                    "0.2715"
                                ],
                                [
                                    "63.1747",
                                    "0.2599"
                                ],
                                [
                                    "59.7614",
                                    "0.2522"
                                ],
                                [
                                    "55.9687",
                                    "0.2445"
                                ],
                                [
                                    "52.1761",
                                    "0.2406"
                                ],
                                [
                                    "48.0042",
                                    "0.2406"
                                ],
                                [
                                    "44.2116",
                                    "0.2367"
                                ],
                                [
                                    "40.4189",
                                    "0.2367"
                                ],
                                [
                                    "36.6263",
                                    "0.2329"
                                ],
                                [
                                    "32.8337",
                                    "0.2290"
                                ],
                                [
                                    "99.2100",
                                    "0.4365"
                                ],
                                [
                                    "96.4308",
                                    "0.4176"
                                ],
                                [
                                    "93.7770",
                                    "0.3989"
                                ],
                                [
                                    "29.2500",
                                    "0.2274"
                                ],
                                [
                                    "26.4708",
                                    "0.2240"
                                ],
                                [
                                    "23.7125",
                                    "0.2217"
                                ],
                                [
                                    "20.5781",
                                    "0.2181"
                                ],
                                [
                                    "18.0497",
                                    "0.2145"
                                ],
                                [
                                    "15.2705",
                                    "0.2051"
                                ],
                                [
                                    "12.6167",
                                    "0.1958"
                                ],
                                [
                                    "9.5032",
                                    "0.1828"
                                ],
                                [
                                    "5.5747",
                                    "0.1675"
                                ],
                                [
                                    "7.4345",
                                    "0.1747"
                                ],
                                [
                                    "3.1508",
                                    "0.1594"
                                ],
                                [
                                    "0.7269",
                                    "0.1524"
                                ]
                            ]
                        }
                    ]
                },
                {
                    "name": "3.9.3、棒材700℃和750℃的蠕变应力与速率关系曲线见图3-6。",
                    "con": ""
                }
            ]
        },
        {
            "name": "3.10、疲劳性能",
            "con": "",
            "two": [
                {
                    "name": "3.10.1、高周疲劳",
                    "con": "棒材700℃和800℃的旋转弯曲光滑和缺口疲劳极限见表3-12。",
                    "tableData": [
                        {
                            "取样/mm": "d22～32热轧棒 双真空熔炼",
                            "状态": "标准热处理",
                            "θ/℃": 700,
                            "光滑疲劳_σ-1/MPa": 363,
                            "光滑疲劳_Nf/周": ">10⁷",
                            "缺口疲劳_σ-1H/MPa①": 275,
                            "缺口疲劳_Nf/周": ">10⁷"
                        },
                        {
                            "取样/mm": "d22～32热轧棒 双真空熔炼",
                            "状态": "标准热处理",
                            "θ/℃": 800,
                            "光滑疲劳_σ-1/MPa": 353,
                            "光滑疲劳_Nf/周": ">10⁷",
                            "缺口疲劳_σ-1H/MPa①": "—",
                            "缺口疲劳_Nf/周": "—"
                        },
                        {
                            "取样/mm": "①缺口半径r=0.75mm"
                        }
                    ],
                    "tableColumns": [
                        {
                            "label": "取样/mm",
                            "prop": "取样/mm"
                        },
                        {
                            "label": "状态",
                            "prop": "状态"
                        },
                        {
                            "label": "θ/℃",
                            "prop": "θ/℃"
                        },
                        {
                            "label": "光滑疲劳_σ-1/MPa",
                            "prop": "光滑疲劳_σ-1/MPa"
                        },
                        {
                            "label": "光滑疲劳_Nf/周",
                            "prop": "光滑疲劳_Nf/周"
                        },
                        {
                            "label": "缺口疲劳_σ-1H/MPa①",
                            "prop": "缺口疲劳_σ-1H/MPa①"
                        },
                        {
                            "label": "缺口疲劳_Nf/周",
                            "prop": "缺口疲劳_Nf/周"
                        }
                    ]
                },
                {
                    "name": "3.10.2、低周疲劳",
                    "con": "无"
                },
                {
                    "name": "3.10.3、特种疲劳",
                    "con": "板材800℃⇄35℃和900℃⇄35℃的冷热疲劳性能见表3-13。",
                    "tableData": [
                        {
                            "取样": "板材 标准热处理",
                            "θ/℃": "800⇆35",
                            "N/周": 124,
                            "裂纹长度/mm": 0.5,
                            "增宽/mm": 0.02
                        },
                        {
                            "取样": "板材 标准热处理",
                            "θ/℃": "900⇆35",
                            "N/周": 71,
                            "裂纹长度/mm": 0.5,
                            "增宽/mm": 0.19
                        }
                    ],
                    "tableColumns": [
                        {
                            "label": "取样",
                            "prop": "取样"
                        },
                        {
                            "label": "θ/℃",
                            "prop": "θ/℃"
                        },
                        {
                            "label": "N/周",
                            "prop": "N/周"
                        },
                        {
                            "label": "裂纹长度/mm",
                            "prop": "裂纹长度/mm"
                        },
                        {
                            "label": "增宽/mm",
                            "prop": "增宽/mm"
                        }
                    ]
                }
            ]
        },
        {
            "name": "3.11、裂纹扩展速率",
            "con": "无"
        },
        {
            "name": "3.12、断裂韧度",
            "con": "无"
        },
        {
            "name": "3.13、松弛性能",
            "con": "无"
        }
    ],
    "craft": [
        {
            "name": "4.1、成形工艺与性能",
            "con": "GH2302合金热加工塑性好，塑性图见图4-1。合金开始再结晶温度高于900℃，为保证获得均匀细小晶粒的锻轧材，终锻（轧）温度应不低于950℃，变形量不小于14%。锻造开坯时装炉温度不高于700℃，加热温度1100℃~1120℃，终锻温度高于950℃。热轧加热温度1100℃~1120℃，终轧温度1000℃~1030℃。",
            "xAxisData": [],
            "echartMsg": {
                "echartId": "41",
                "xName": "",
                "yName": "",
                "minX": 901.2495,
                "minY": 9.5273
            },
            "seriesData": [
                {
                    "name": "ψ-θ",
                    "type": "line",
                    "smooth": "smooth",
                    "data": [
                        [
                            "949.7678",
                            "74.1189"
                        ],
                        [
                            "901.2495",
                            "16.7806"
                        ],
                        [
                            "1051.8274",
                            "97.7858"
                        ],
                        [
                            "1101.0306",
                            "67.2095"
                        ],
                        [
                            "1152.0604",
                            "34.5699"
                        ]
                    ]
                },
                {
                    "name": "δ5-θ",
                    "type": "line",
                    "smooth": "smooth",
                    "data": [
                        [
                            "902.5053",
                            "9.5273"
                        ],
                        [
                            "1002.7383",
                            "88.2815"
                        ],
                        [
                            "1000.7976",
                            "91.2204"
                        ],
                        [
                            "1049.3158",
                            "92.9399"
                        ],
                        [
                            "1099.7748",
                            "60.1439"
                        ],
                        [
                            "1152.7453",
                            "21.4389"
                        ]
                    ]
                },
                {
                    "name": "ε-θ",
                    "type": "line",
                    "smooth": "smooth",
                    "data": [
                        [
                            "1207.5424",
                            "12.1222"
                        ],
                        [
                            "1153.3161",
                            "45.2622"
                        ],
                        [
                            "1101.0306",
                            "54.0786"
                        ],
                        [
                            "1052.5123",
                            "53.3908"
                        ],
                        [
                            "1002.7383",
                            "57.5489"
                        ]
                    ]
                },
                {
                    "name": "σKU-θ",
                    "type": "line",
                    "smooth": "smooth",
                    "data": [
                        [
                            "1000.2268",
                            "1337.3129"
                        ],
                        [
                            "954.1059",
                            "642.6251"
                        ],
                        [
                            "1050.5716",
                            "974.6496"
                        ],
                        [
                            "1100.4598",
                            "940.2591"
                        ],
                        [
                            "1150.8046",
                            "279.9619"
                        ],
                        [
                            "1199.4370",
                            "66.1156"
                        ]
                    ]
                }
            ]
        },
        {
            "name": "4.2、工艺性能",
            "con": "薄板的反复弯曲性能见表4-1。",
            "tableData": [
                {
                    "板厚/mm": 1.5,
                    "热处理": "—",
                    "时效规范": "1100℃×10min/AC",
                    "反复弯曲/次数": 17
                },
                {
                    "板厚/mm": 1.5,
                    "热处理": "标准热处理",
                    "时效规范": "—",
                    "反复弯曲/次数": 8.2
                },
                {
                    "板厚/mm": 1.5,
                    "热处理": "标准热处理",
                    "时效规范": "800℃×100h/AC",
                    "反复弯曲/次数": 3.7
                },
                {
                    "板厚/mm": 1.5,
                    "热处理": "标准热处理",
                    "时效规范": "800℃×400h/AC",
                    "反复弯曲/次数": 2
                },
                {
                    "板厚/mm": 1.5,
                    "热处理": "标准热处理",
                    "时效规范": "850℃×100h/AC",
                    "反复弯曲/次数": 1.8
                },
                {
                    "板厚/mm": 1.5,
                    "热处理": "标准热处理",
                    "时效规范": "850℃×200h/AC",
                    "反复弯曲/次数": 1.3
                },
                {
                    "板厚/mm": "注：r=7.5mm；h=20mm；弯曲半径5倍于板材厚度。"
                }
            ],
            "tableColumns": [
                {
                    "label": "板厚/mm",
                    "prop": "板厚/mm"
                },
                {
                    "label": "热处理",
                    "prop": "热处理"
                },
                {
                    "label": "时效规范",
                    "prop": "时效规范"
                },
                {
                    "label": "反复弯曲/次数",
                    "prop": "反复弯曲/次数"
                }
            ]
        },
        {
            "name": "4.3、焊接性能",
            "con": "合金氩弧焊接头强度见表4-2。",
            "tableData": [
                {
                    "板厚/mm": "1.5+1.5",
                    "焊丝": "SHG-1",
                    "状态": "焊前固溶 焊后时效",
                    "接头20℃拉伸_σb/MPa": 1227,
                    "接头20℃拉伸_强度系数/%": 96.3,
                    "接头800℃拉伸_σb/MPa": 669,
                    "接头800℃拉伸_强度系数/%": 98.9,
                    "接头800℃、215MPa持久_τ/h": 150,
                    "接头800℃、215MPa持久_强度系数": "5～100"
                },
                {
                    "板厚/mm": 1.5,
                    "焊丝": "—",
                    "状态": "焊前固溶 焊后时效",
                    "接头20℃拉伸_σb/MPa": 1270,
                    "接头20℃拉伸_强度系数/%": 96.3,
                    "接头800℃拉伸_σb/MPa": 677,
                    "接头800℃拉伸_强度系数/%": 98.9,
                    "接头800℃、215MPa持久_τ/h": 162,
                    "接头800℃、215MPa持久_强度系数": "5～100"
                }
            ],
            "tableColumns": [
                {
                    "label": "板厚/mm",
                    "prop": "板厚/mm"
                },
                {
                    "label": "焊丝",
                    "prop": "焊丝"
                },
                {
                    "label": "状态",
                    "prop": "状态"
                },
                {
                    "label": "接头20℃拉伸_σb/MPa",
                    "prop": "接头20℃拉伸_σb/MPa"
                },
                {
                    "label": "接头20℃拉伸_强度系数/%",
                    "prop": "接头20℃拉伸_强度系数/%"
                },
                {
                    "label": "接头800℃拉伸_σb/MPa",
                    "prop": "接头800℃拉伸_σb/MPa"
                },
                {
                    "label": "接头800℃拉伸_强度系数/%",
                    "prop": "接头800℃拉伸_强度系数/%"
                },
                {
                    "label": "接头800℃、215MPa持久_τ/h",
                    "prop": "接头800℃、215MPa持久_τ/h"
                },
                {
                    "label": "接头800℃、215MPa持久_强度系数",
                    "prop": "接头800℃、215MPa持久_强度系数"
                }
            ]
        },
        {
            "name": "4.4、零件热处理工艺",
            "con": "同各品种的标准热处理制度。"
        },
        {
            "name": "4.5、表面处理工艺",
            "con": "",
            "two": [
                {
                    "name": "4.5.1、固体渗Al工艺：将零件埋入渗Al剂中，经800℃×8h，渗Al厚度约为8μm～9μm。渗Al剂Al:Fe:NH4Cl=45:55:1。渗Al后其力学性能与未渗Al的相近。",
                    "con": ""
                },
                {
                    "name": "4.5.2、料浆-粉末法渗Al工艺：镍基或钴基料浆成分见表4-3，把料浆喷涂到工件表面，然后埋在CrAl活性渗剂中进行扩散处理，加热制度可以结合时效处理进行。活性渗剂组成为：48%Cr粉+8%Al粉+42%Al₂O₃粉+2%NH4Cl。",
                    "con": "",
                    "tableData": [
                        {
                            "料浆种类": "镍基料浆",
                            "料浆成分(质量分数)/%_Ni": 60,
                            "料浆成分(质量分数)/%_Cr": 20,
                            "料浆成分(质量分数)/%_Al": 6,
                            "料浆成分(质量分数)/%_Si": 2,
                            "料浆成分(质量分数)/%_Co": 10,
                            "料浆成分(质量分数)/%_NH4Cl": 1,
                            "料浆成分(质量分数)/%_硝化纤维": 1
                        },
                        {
                            "料浆种类": "钴基料浆",
                            "料浆成分(质量分数)/%_Ni": 10,
                            "料浆成分(质量分数)/%_Cr": 25,
                            "料浆成分(质量分数)/%_Al": 6,
                            "料浆成分(质量分数)/%_Si": 2,
                            "料浆成分(质量分数)/%_Co": 55,
                            "料浆成分(质量分数)/%_NH4Cl": 1,
                            "料浆成分(质量分数)/%_硝化纤维": 1
                        }
                    ],
                    "tableColumns": [
                        {
                            "label": "料浆种类",
                            "prop": "料浆种类"
                        },
                        {
                            "label": "料浆成分(质量分数)/%_Ni",
                            "prop": "料浆成分(质量分数)/%_Ni"
                        },
                        {
                            "label": "料浆成分(质量分数)/%_Cr",
                            "prop": "料浆成分(质量分数)/%_Cr"
                        },
                        {
                            "label": "料浆成分(质量分数)/%_Al",
                            "prop": "料浆成分(质量分数)/%_Al"
                        },
                        {
                            "label": "料浆成分(质量分数)/%_Si",
                            "prop": "料浆成分(质量分数)/%_Si"
                        },
                        {
                            "label": "料浆成分(质量分数)/%_Co",
                            "prop": "料浆成分(质量分数)/%_Co"
                        },
                        {
                            "label": "料浆成分(质量分数)/%_NH4Cl",
                            "prop": "料浆成分(质量分数)/%_NH4Cl"
                        },
                        {
                            "label": "料浆成分(质量分数)/%_硝化纤维",
                            "prop": "料浆成分(质量分数)/%_硝化纤维"
                        }
                    ]
                }
            ]
        },
        {
            "name": "4.6、切削加工与磨削性能",
            "con": "",
            "two": [
                {
                    "name": "4.6.1、两种合金在端铣加工时，刀具寿命与切削速度的关系见图4-2。在同样切削速度下(14.1m/min)，端铣GH2302合金的刀具寿命比GH4037合金高3倍。",
                    "con": ""
                },
                {
                    "name": "4.6.2、磨削性能见图4-3。",
                    "con": "",
                    "xAxisData": [],
                    "echartMsg": {
                        "echartId": "462",
                        "xName": "",
                        "yName": "",
                        "minX": 0.0046,
                        "minY": 1.7409
                    },
                    "seriesData": [
                        {
                            "name": "Qu-磨削深度",
                            "type": "line",
                            "smooth": "smooth",
                            "data": [
                                [
                                    "0.0147",
                                    "536.0666"
                                ],
                                [
                                    "0.0096",
                                    "471.2640"
                                ],
                                [
                                    "0.0047",
                                    "225.2279"
                                ]
                            ]
                        },
                        {
                            "name": "Qk-磨削深度",
                            "type": "line",
                            "smooth": "smooth",
                            "data": [
                                [
                                    "0.0048",
                                    "84.5744"
                                ],
                                [
                                    "0.0097",
                                    "224.2381"
                                ],
                                [
                                    "0.0146",
                                    "285.3021"
                                ]
                            ]
                        },
                        {
                            "name": "T-磨削深度",
                            "type": "line",
                            "smooth": "smooth",
                            "data": [
                                [
                                    "0.0046",
                                    "6.0696"
                                ],
                                [
                                    "0.0097",
                                    "3.7194"
                                ],
                                [
                                    "0.0147",
                                    "3.2270"
                                ]
                            ]
                        },
                        {
                            "name": "q-磨削深度",
                            "type": "line",
                            "smooth": "smooth",
                            "data": [
                                [
                                    "0.0047",
                                    "2.8779"
                                ],
                                [
                                    "0.0097",
                                    "1.8886"
                                ],
                                [
                                    "0.0147",
                                    "1.7409"
                                ]
                            ]
                        }
                    ]
                }
            ]
        },
        {
            "name": "4.7、模拟试验性能",
            "con": "",
            "two": [
                {
                    "name": "4.7.1、模拟发动机突然升温和加力的实际情况进行持久试验，试验结果见表4-4。",
                    "con": "",
                    "tableData": [
                        {
                            "模拟持久试验条件": "(750℃、137MPa、300h)→(快速) (890℃、176MPa、2min)→ (750℃、137MPa、500h)→ (890℃、176MPa、2min)→ (750℃、137MPa、800h)→ (890℃、176MPa、2min)→ (850℃、196MPa，直到拉断)",
                            "持久总时间τ/h": 953,
                            "δ5/%": 16,
                            "ψ/%": 25
                        }
                    ],
                    "tableColumns": [
                        {
                            "label": "模拟持久试验条件",
                            "prop": "模拟持久试验条件"
                        },
                        {
                            "label": "持久总时间τ/h",
                            "prop": "持久总时间τ/h"
                        },
                        {
                            "label": "δ5/%",
                            "prop": "δ5/%"
                        },
                        {
                            "label": "ψ/%",
                            "prop": "ψ/%"
                        }
                    ]
                },
                {
                    "name": "4.7.2、棒材取样，在800℃、280MPa下进行热冲击试验，至400次时破坏。",
                    "con": ""
                }
            ]
        }
    ],
    "microstructures": [
        {
            "name": "5.1、相变温度",
            "con": "γ'相析出峰值温度为800℃,约1000℃完全溶解；Laves 析出温度大约在700℃~850℃。"
        },
        {
            "name": "5.2、时间- 温度-组织转变曲线",
            "con": "无"
        },
        {
            "name": "5.3、典型组织",
            "con": "合金标准热处理状态组织由γ奥氏体、γ'相、MC 和 M6C型碳化物、M₃B₂型硼化物组成，晶粒度为(1～4)级(图5-1)。γ'相为主要强化相，呈球状，弥散均匀分布(图5-2),大小约为550A,w(γ)约占合金的16%,化学式为(Ni0.95Fe0.05Cr0.01)2.97(Ti0.54Al0.44W0.02Mo0.002)[4]。合金经750℃×10000h 长期时效后，γ相略有长大，析出量没有什么变化；MC 分解，并在其周围析出 M6C 。 晶内普遍析出竹叶状或短棒状 Laves相(图5-3),Laves相属于Fe₂W型，其化学组成式近似为 (Fe0.5~0.6Cr0.25~0.30Ni0.1~0.25)1.8~1.9(W0.5Mo0.5)[4] 。叶片经试车后的组织和析出相的形貌见图5-4。"
        }
    ]
}