{
    "introduce": [
        {
            "name": "1.1、概述",
            "con": "GH4586是Ni-Cr-Co基沉淀硬化型变形高温合金，使用温度范围-196℃~800℃，并可在850℃下短时使用。合金加入铝、钛元素形成γ沉淀强化相，加入钴、铬、钨和钼元素进行固溶强化。合金在合适的热加工和热处理工艺条件下，沿晶界析出细小颗粒状碳化物，起到补充强化的效果。合金具有较高的高温强度，并具有较好的抗氧化、耐腐蚀和抗烧蚀能力，以及良好的热加工和焊接性能。主要产品有棒材、圆饼和模锻件等。"
        },
        {
            "name": "1.2、应用概况及特性",
            "con": "该合金是我国自行研制具有自主知识产权的一种高性能高温合金涡轮盘材料，已用于制作航空、航天等领域发动机用耐热承力件，包括液氧/煤油火箭发动机用涡轮转子以及多种型号航天发动机涡轮转子模锻件，使用情况良好。"
        },
        {
            "name": "1.3、材料牌号",
            "con": "GH4586(GH586)。"
        },
        {
            "name": "1.4、相近牌号",
            "con": "无。"
        },
        {
            "name": "1.5、材料技术标准",
            "con": "GB/T 14992 高温合金和金属间化合物高温材料的分类和牌号@@Q/GYB 05010 GH4586 合金热轧和锻制棒材@@Q/GYB 05021 GH4586 合金锻制圆饼@@Q/GYB 05024 GH4586 合金模锻件"
        },
        {
            "name": "1.6、熔炼工艺",
            "con": "采用真空感应炉+真空自耗重熔双联熔炼工艺。"
        },
        {
            "name": "1.7、化学成分",
            "con": "摘自GB/T 14992，杂质元素分析有区别的摘自Q/GYB 05010、Q/GYB 05021和Q/GYB 05024，见表1-1。",
            "tableData": [
                {
                    "元素": "质量分数/%",
                    "C": "≤0.08",
                    "Cr": "18.00～20.00",
                    "Ni": "余",
                    "Co": "10.00～12.00",
                    "W": "2.00～4.00",
                    "Mo": "7.00～9.00",
                    "A1": "1.50～1.70",
                    "Ti": "3.20～3.50",
                    "Fe": "≤5.00",
                    "La": "≤0.015",
                    "B": "≤0.005",
                    "Mg": "≤0.015",
                    "Mn": "≤0.10",
                    "Si": "≤0.50",
                    "S": "≤0.010",
                    "P": "≤0.010",
                    "Pb": "≤0.001",
                    "Sb": "≤0.0025",
                    "Sn": "≤0.0012",
                    "Bi": "≤0.001",
                    "As": "≤0.0025"
                },
                {
                    "元素": "①Q/GYB 05010、Q/GYB 05021和Q/GYB 05024规定检验的杂质元素。"
                }
            ],
            "tableColumns": [
                {
                    "label": "元素",
                    "prop": "元素"
                },
                {
                    "label": "C",
                    "prop": "C"
                },
                {
                    "label": "Cr",
                    "prop": "Cr"
                },
                {
                    "label": "Ni",
                    "prop": "Ni"
                },
                {
                    "label": "Co",
                    "prop": "Co"
                },
                {
                    "label": "W",
                    "prop": "W"
                },
                {
                    "label": "Mo",
                    "prop": "Mo"
                },
                {
                    "label": "A1",
                    "prop": "A1"
                },
                {
                    "label": "Ti",
                    "prop": "Ti"
                },
                {
                    "label": "Fe",
                    "prop": "Fe"
                },
                {
                    "label": "La",
                    "prop": "La"
                },
                {
                    "label": "B",
                    "prop": "B"
                },
                {
                    "label": "Mg",
                    "prop": "Mg"
                },
                {
                    "label": "Mn",
                    "prop": "Mn"
                },
                {
                    "label": "Si",
                    "prop": "Si"
                },
                {
                    "label": "S",
                    "prop": "S"
                },
                {
                    "label": "P",
                    "prop": "P"
                },
                {
                    "label": "Pb",
                    "prop": "Pb"
                },
                {
                    "label": "Sb",
                    "prop": "Sb"
                },
                {
                    "label": "Sn",
                    "prop": "Sn"
                },
                {
                    "label": "Bi",
                    "prop": "Bi"
                },
                {
                    "label": "As",
                    "prop": "As"
                }
            ]
        },
        {
            "name": "1.8、热处理制度",
            "con": "摘自Q/GY B05010、Q/GYB 05021和Q/GYB 05024，热轧和锻制棒材、锻制圆饼，模锻件的标准热处理制度为：1080℃±20℃×4h/AC+760℃±10℃×4h/AC。"
        },
        {
            "name": "1.9、品种规格与供应状态",
            "con": "",
            "two": [
                {
                    "name": "1.9.1、品种规格与供应状态",
                    "con": "摘自Q/GYB 05010、Q/GYB 05021和Q/GYB 05024。"
                },
                {
                    "name": "1.9.2、主要规格",
                    "con": "d10mm~300mm热轧和锻制棒材；d150mm~600mm锻制圆饼；d100mm~630mm模锻件。"
                },
                {
                    "name": "1.9.3、供应状态",
                    "con": "棒材一般不经热处理供应；锻制圆饼和模锻件一般不经热处理供应，也可经热处理+机加工后供应。"
                }
            ]
        }
    ],
    "physicalChemistry": [
        {
            "name": "2.1、熔化温度范围",
            "con": "1317℃~1342℃"
        },
        {
            "name": "2.2、相变点",
            "con": "无。"
        },
        {
            "name": "2.3、热导率",
            "con": "表2-1",
            "tableData": [
                {
                    "100": 12.34,
                    "200": 13.93,
                    "300": 15.48,
                    "400": 17.03,
                    "500": 18.62,
                    "600": 20.29,
                    "700": 21.76,
                    "800": 23.43,
                    "900": 25.02,
                    "θ/℃": "λ/[W/(m·℃)]"
                }
            ],
            "tableColumns": [
                {
                    "label": "100",
                    "prop": "100"
                },
                {
                    "label": "200",
                    "prop": "200"
                },
                {
                    "label": "300",
                    "prop": "300"
                },
                {
                    "label": "400",
                    "prop": "400"
                },
                {
                    "label": "500",
                    "prop": "500"
                },
                {
                    "label": "600",
                    "prop": "600"
                },
                {
                    "label": "700",
                    "prop": "700"
                },
                {
                    "label": "800",
                    "prop": "800"
                },
                {
                    "label": "900",
                    "prop": "900"
                },
                {
                    "label": "θ/℃",
                    "prop": "θ/℃"
                }
            ]
        },
        {
            "name": "2.4、电阻率",
            "con": "表2-2",
            "tableData": [
                {
                    "20": 126.71,
                    "100": 130.32,
                    "200": 132,
                    "300": 134.46,
                    "400": 137.25,
                    "500": 139.01,
                    "600": 141.28,
                    "700": 141.49,
                    "800": 141.45,
                    "900": 142.42,
                    "θ/℃": "ρ/(10^（-6）Ω·cm)"
                }
            ],
            "tableColumns": [
                {
                    "label": "20",
                    "prop": "20"
                },
                {
                    "label": "100",
                    "prop": "100"
                },
                {
                    "label": "200",
                    "prop": "200"
                },
                {
                    "label": "300",
                    "prop": "300"
                },
                {
                    "label": "400",
                    "prop": "400"
                },
                {
                    "label": "500",
                    "prop": "500"
                },
                {
                    "label": "600",
                    "prop": "600"
                },
                {
                    "label": "700",
                    "prop": "700"
                },
                {
                    "label": "800",
                    "prop": "800"
                },
                {
                    "label": "900",
                    "prop": "900"
                },
                {
                    "label": "θ/℃",
                    "prop": "θ/℃"
                }
            ]
        },
        {
            "name": "2.5、热扩散率",
            "con": "无。"
        },
        {
            "name": "2.6、比热容",
            "con": "无。"
        },
        {
            "name": "2.7、线膨胀系数",
            "con": "表2-3",
            "tableData": [
                {
                    "θ/℃": "α/(10^（-6）℃^（-1）)",
                    "20～100": 11.49,
                    "20～200": 11.82,
                    "20～300": 12.38,
                    "20～400": 12.8,
                    "20～500": 13.11,
                    "20～600": 13.45,
                    "20～700": 14.06,
                    "20～800": 14.69,
                    "20～900": 15.73,
                    "20～600_1": 13.45,
                    "20～700_1": 14.06,
                    "20～800_1": 14.69,
                    "20～900_1": 15.73
                }
            ],
            "tableColumns": [
                {
                    "label": "θ/℃",
                    "prop": "θ/℃"
                },
                {
                    "label": "20～100",
                    "prop": "20～100"
                },
                {
                    "label": "20～200",
                    "prop": "20～200"
                },
                {
                    "label": "20～300",
                    "prop": "20～300"
                },
                {
                    "label": "20～400",
                    "prop": "20～400"
                },
                {
                    "label": "20～500",
                    "prop": "20～500"
                },
                {
                    "label": "20～600",
                    "prop": "20～600"
                },
                {
                    "label": "20～700",
                    "prop": "20～700"
                },
                {
                    "label": "20～800",
                    "prop": "20～800"
                },
                {
                    "label": "20～900",
                    "prop": "20～900"
                },
                {
                    "label": "20～600_1",
                    "prop": "20～600_1"
                },
                {
                    "label": "20～700_1",
                    "prop": "20～700_1"
                },
                {
                    "label": "20～800_1",
                    "prop": "20～800_1"
                },
                {
                    "label": "20～900_1",
                    "prop": "20～900_1"
                }
            ]
        },
        {
            "name": "2.8、密度",
            "con": "ρ=8.39g/cm³。"
        },
        {
            "name": "2.9、磁性能",
            "con": "合金无磁性。"
        },
        {
            "name": "2.10、弹性性能",
            "con": "表2-4",
            "tableData": [
                {
                    "20": 226,
                    "100": 222,
                    "200": 217,
                    "300": 211,
                    "400": 205,
                    "500": 198,
                    "600": 192,
                    "700": 184,
                    "800": 178,
                    "900": 162,
                    "θ/℃": "ED/GPa"
                }
            ],
            "tableColumns": [
                {
                    "label": "20",
                    "prop": "20"
                },
                {
                    "label": "100",
                    "prop": "100"
                },
                {
                    "label": "200",
                    "prop": "200"
                },
                {
                    "label": "300",
                    "prop": "300"
                },
                {
                    "label": "400",
                    "prop": "400"
                },
                {
                    "label": "500",
                    "prop": "500"
                },
                {
                    "label": "600",
                    "prop": "600"
                },
                {
                    "label": "700",
                    "prop": "700"
                },
                {
                    "label": "800",
                    "prop": "800"
                },
                {
                    "label": "900",
                    "prop": "900"
                },
                {
                    "label": "θ/℃",
                    "prop": "θ/℃"
                }
            ]
        },
        {
            "name": "2.11、抗氧化性能",
            "con": "合金在空气介质中，不同温度试验不同时间的氧化速率见表2-5。",
            "tableData": [
                {
                    "θ/℃": 800,
                    "25h，氧化速率/[g/(m·h)]": 0.0731,
                    "50h，氧化速率/[g/(m·h)]": 0.0535,
                    "75h，氧化速率/[g/(m·h)]": 0.0467,
                    "100h，氧化速率/[g/(m·h)]": 0.0376
                },
                {
                    "θ/℃": 900,
                    "25h，氧化速率/[g/(m·h)]": 0.214,
                    "50h，氧化速率/[g/(m·h)]": 0.1745,
                    "75h，氧化速率/[g/(m·h)]": 0.146,
                    "100h，氧化速率/[g/(m·h)]": 0.1255
                },
                {
                    "θ/℃": 1000,
                    "25h，氧化速率/[g/(m·h)]": 0.4686,
                    "50h，氧化速率/[g/(m·h)]": 0.3523,
                    "75h，氧化速率/[g/(m·h)]": 0.2709,
                    "100h，氧化速率/[g/(m·h)]": 0.24
                },
                {
                    "θ/℃": 1100,
                    "25h，氧化速率/[g/(m·h)]": 1.1818,
                    "50h，氧化速率/[g/(m·h)]": 0.8175,
                    "75h，氧化速率/[g/(m·h)]": 0.6512,
                    "100h，氧化速率/[g/(m·h)]": 0.5323
                }
            ],
            "tableColumns": [
                {
                    "label": "θ/℃",
                    "prop": "θ/℃"
                },
                {
                    "label": "25h，氧化速率/[g/(m·h)]",
                    "prop": "25h，氧化速率/[g/(m·h)]"
                },
                {
                    "label": "50h，氧化速率/[g/(m·h)]",
                    "prop": "50h，氧化速率/[g/(m·h)]"
                },
                {
                    "label": "75h，氧化速率/[g/(m·h)]",
                    "prop": "75h，氧化速率/[g/(m·h)]"
                },
                {
                    "label": "100h，氧化速率/[g/(m·h)]",
                    "prop": "100h，氧化速率/[g/(m·h)]"
                }
            ]
        },
        {
            "name": "2.12、耐腐蚀性能",
            "con": "无。"
        }
    ],
    "mechanical": [
        {
            "name": "3.1、供货技术标准",
            "con": "",
            "two": [
                {
                    "name": "3.1.1、技术标准规定的性能",
                    "con": "表3-1",
                    "tableData": [
                        {
                            "标准号": "标准号",
                            "品种": "品种",
                            "热处理": "热处理",
                            "θ/℃": "θ/℃",
                            "取样方向": "取样方向",
                            "拉伸性能_σb/MPa": "≥",
                            "拉伸性能_σP0.2/MPa": "≥",
                            "拉伸性能_δ5/%": "≥",
                            "拉伸性能_ψ/%": "≥",
                            "室温性能_AK/J": "≥",
                            "室温性能_HBW": "室温性能_HBW",
                            "持久性能_σ/MPa": "持久性能_σ/MPa",
                            "持久性能_τ/h": "≥",
                            "持久性能_δ5/%": "≥",
                            "持久性能_ψ/%": "≥"
                        },
                        {
                            "标准号": "Q/GYB 05010",
                            "品种": "棒材",
                            "热处理": "标准热处理",
                            "θ/℃": 20,
                            "取样方向": "-",
                            "拉伸性能_σb/MPa": 1250,
                            "拉伸性能_σP0.2/MPa": 920,
                            "拉伸性能_δ5/%": 12,
                            "拉伸性能_ψ/%": 15,
                            "室温性能_AK/J": 16,
                            "室温性能_HBW": 340,
                            "持久性能_σ/MPa": "-",
                            "持久性能_τ/h": "-",
                            "持久性能_δ5/%": "-",
                            "持久性能_ψ/%": "-"
                        },
                        {
                            "标准号": "Q/GYB 05010",
                            "品种": "棒材",
                            "热处理": "标准热处理",
                            "θ/℃": 600,
                            "取样方向": "-",
                            "拉伸性能_σb/MPa": 1160,
                            "拉伸性能_σP0.2/MPa": 830,
                            "拉伸性能_δ5/%": 12,
                            "拉伸性能_ψ/%": 15,
                            "室温性能_AK/J": "-",
                            "室温性能_HBW": "-",
                            "持久性能_σ/MPa": 920,
                            "持久性能_τ/h": "≥23",
                            "持久性能_δ5/%": "实测",
                            "持久性能_ψ/%": "实测"
                        },
                        {
                            "标准号": "Q/GYB 05010",
                            "品种": "棒材",
                            "热处理": "标准热处理",
                            "θ/℃": -196,
                            "取样方向": "-",
                            "拉伸性能_σb/MPa": 1400,
                            "拉伸性能_σP0.2/MPa": 1000,
                            "拉伸性能_δ5/%": 8,
                            "拉伸性能_ψ/%": 10,
                            "室温性能_AK/J": 10,
                            "室温性能_HBW": "-",
                            "持久性能_σ/MPa": "-",
                            "持久性能_τ/h": "-",
                            "持久性能_δ5/%": "-",
                            "持久性能_ψ/%": "-"
                        },
                        {
                            "标准号": "Q/GYB 05021",
                            "品种": "圆饼",
                            "热处理": "标准热处理",
                            "θ/℃": 20,
                            "取样方向": "弦向",
                            "拉伸性能_σb/MPa": 1250,
                            "拉伸性能_σP0.2/MPa": 920,
                            "拉伸性能_δ5/%": 12,
                            "拉伸性能_ψ/%": 15,
                            "室温性能_AK/J": 16,
                            "室温性能_HBW": 340,
                            "持久性能_σ/MPa": "-",
                            "持久性能_τ/h": "-",
                            "持久性能_δ5/%": "-",
                            "持久性能_ψ/%": "-"
                        },
                        {
                            "标准号": "Q/GYB 05021",
                            "品种": "圆饼",
                            "热处理": "标准热处理",
                            "θ/℃": 20,
                            "取样方向": "径向",
                            "拉伸性能_σb/MPa": "实测",
                            "拉伸性能_σP0.2/MPa": "实测",
                            "拉伸性能_δ5/%": "实测",
                            "拉伸性能_ψ/%": "实测",
                            "室温性能_AK/J": "-",
                            "室温性能_HBW": 340,
                            "持久性能_σ/MPa": "-",
                            "持久性能_τ/h": "-",
                            "持久性能_δ5/%": "-",
                            "持久性能_ψ/%": "-"
                        },
                        {
                            "标准号": "Q/GYB 05021",
                            "品种": "圆饼",
                            "热处理": "标准热处理",
                            "θ/℃": 500,
                            "取样方向": "弦向",
                            "拉伸性能_σb/MPa": "实测",
                            "拉伸性能_σP0.2/MPa": "实测",
                            "拉伸性能_δ5/%": "实测",
                            "拉伸性能_ψ/%": "实测",
                            "室温性能_AK/J": "-",
                            "室温性能_HBW": "-",
                            "持久性能_σ/MPa": "-",
                            "持久性能_τ/h": "-",
                            "持久性能_δ5/%": "-",
                            "持久性能_ψ/%": "-"
                        },
                        {
                            "标准号": "Q/GYB 05021",
                            "品种": "圆饼",
                            "热处理": "标准热处理",
                            "θ/℃": 600,
                            "取样方向": "弦向",
                            "拉伸性能_σb/MPa": 1160,
                            "拉伸性能_σP0.2/MPa": 830,
                            "拉伸性能_δ5/%": 12,
                            "拉伸性能_ψ/%": 15,
                            "室温性能_AK/J": "-",
                            "室温性能_HBW": "-",
                            "持久性能_σ/MPa": 920,
                            "持久性能_τ/h": "≥23",
                            "持久性能_δ5/%": "实测",
                            "持久性能_ψ/%": "实测"
                        },
                        {
                            "标准号": "Q/GYB 05021",
                            "品种": "圆饼",
                            "热处理": "标准热处理",
                            "θ/℃": -196,
                            "取样方向": "弦向",
                            "拉伸性能_σb/MPa": 1400,
                            "拉伸性能_σP0.2/MPa": 1000,
                            "拉伸性能_δ5/%": 8,
                            "拉伸性能_ψ/%": 12,
                            "室温性能_AK/J": 10,
                            "持久性能_σ/MPa": "-",
                            "持久性能_τ/h": "-",
                            "持久性能_δ5/%": "-",
                            "持久性能_ψ/%": "-"
                        },
                        {
                            "标准号": "Q/GYB 05024",
                            "品种": "模锻件",
                            "热处理": "标准热处理",
                            "θ/℃": 20,
                            "取样方向": "盘弦向",
                            "拉伸性能_σb/MPa": 1250,
                            "拉伸性能_σP0.2/MPa": 920,
                            "拉伸性能_δ5/%": 12,
                            "拉伸性能_ψ/%": 12,
                            "室温性能_AK/J": 16,
                            "室温性能_HBW": 340,
                            "持久性能_σ/MPa": "-",
                            "持久性能_τ/h": "-",
                            "持久性能_δ5/%": "-",
                            "持久性能_ψ/%": "-"
                        },
                        {
                            "标准号": "Q/GYB 05024",
                            "品种": "模锻件",
                            "热处理": "标准热处理",
                            "θ/℃": 20,
                            "取样方向": "轴径向",
                            "拉伸性能_σb/MPa": "-",
                            "拉伸性能_σP0.2/MPa": "-",
                            "拉伸性能_δ5/%": "-",
                            "拉伸性能_ψ/%": "-",
                            "室温性能_AK/J": 16,
                            "室温性能_HBW": "-",
                            "持久性能_σ/MPa": "-",
                            "持久性能_τ/h": "-",
                            "持久性能_δ5/%": "-",
                            "持久性能_ψ/%": "-"
                        },
                        {
                            "标准号": "Q/GYB 05024",
                            "品种": "模锻件",
                            "热处理": "标准热处理",
                            "θ/℃": 850,
                            "取样方向": "盘弦向",
                            "拉伸性能_σb/MPa": 760,
                            "拉伸性能_σP0.2/MPa": 660,
                            "拉伸性能_δ5/%": 12,
                            "拉伸性能_ψ/%": 12,
                            "室温性能_AK/J": "-",
                            "室温性能_HBW": "-",
                            "持久性能_σ/MPa": 580,
                            "持久性能_τ/h": "≥0.4",
                            "持久性能_δ5/%": "实测",
                            "持久性能_ψ/%": "实测"
                        }
                    ],
                    "tableColumns": [
                        {
                            "label": "标准号",
                            "prop": "标准号"
                        },
                        {
                            "label": "品种",
                            "prop": "品种"
                        },
                        {
                            "label": "热处理",
                            "prop": "热处理"
                        },
                        {
                            "label": "θ/℃",
                            "prop": "θ/℃"
                        },
                        {
                            "label": "取样方向",
                            "prop": "取样方向"
                        },
                        {
                            "label": "拉伸性能_σb/MPa",
                            "prop": "拉伸性能_σb/MPa"
                        },
                        {
                            "label": "拉伸性能_σP0.2/MPa",
                            "prop": "拉伸性能_σP0.2/MPa"
                        },
                        {
                            "label": "拉伸性能_δ5/%",
                            "prop": "拉伸性能_δ5/%"
                        },
                        {
                            "label": "拉伸性能_ψ/%",
                            "prop": "拉伸性能_ψ/%"
                        },
                        {
                            "label": "室温性能_AK/J",
                            "prop": "室温性能_AK/J"
                        },
                        {
                            "label": "室温性能_HBW",
                            "prop": "室温性能_HBW"
                        },
                        {
                            "label": "持久性能_σ/MPa",
                            "prop": "持久性能_σ/MPa"
                        },
                        {
                            "label": "持久性能_τ/h",
                            "prop": "持久性能_τ/h"
                        },
                        {
                            "label": "持久性能_δ5/%",
                            "prop": "持久性能_δ5/%"
                        },
                        {
                            "label": "持久性能_ψ/%",
                            "prop": "持久性能_ψ/%"
                        }
                    ]
                },
                {
                    "name": "3.1.2、生产检验数据、基值和设计许用值",
                    "con": "无。"
                }
            ]
        },
        {
            "name": "3.2、硬度",
            "con": "无。"
        },
        {
            "name": "3.3、冲击性能",
            "con": "圆饼不同温度的冲击韧性见表3-2。",
            "tableData": [
                {
                    "取样": "圆饼弦向 标准热处理",
                    "θ/℃": -196,
                    "αK/(J/cm^2)": 27.5
                },
                {
                    "取样": "圆饼弦向 标准热处理",
                    "θ/℃": 20,
                    "αK/(J/cm^2)": 44.4
                },
                {
                    "取样": "圆饼弦向 标准热处理",
                    "θ/℃": 250,
                    "αK/(J/cm^2)": 57
                },
                {
                    "取样": "圆饼弦向 标准热处理",
                    "θ/℃": 550,
                    "αK/(J/cm^2)": 58.9
                },
                {
                    "取样": "圆饼弦向 标准热处理",
                    "θ/℃": 650,
                    "αK/(J/cm^2)": 50.5
                },
                {
                    "取样": "圆饼弦向 标准热处理",
                    "θ/℃": 700,
                    "αK/(J/cm^2)": 55.2
                },
                {
                    "取样": "圆饼弦向 标准热处理",
                    "θ/℃": 750,
                    "αK/(J/cm^2)": 43.6
                },
                {
                    "取样": "圆饼弦向 标准热处理",
                    "θ/℃": 800,
                    "αK/(J/cm^2)": 45.7
                },
                {
                    "取样": "圆饼弦向 标准热处理",
                    "θ/℃": 850,
                    "αK/(J/cm^2)": 48
                },
                {
                    "取样": "圆饼弦向 标准热处理",
                    "θ/℃": 900,
                    "αK/(J/cm^2)": 54
                }
            ],
            "tableColumns": [
                {
                    "label": "取样",
                    "prop": "取样"
                },
                {
                    "label": "θ/℃",
                    "prop": "θ/℃"
                },
                {
                    "label": "αK/(J/cm^2)",
                    "prop": "αK/(J/cm^2)"
                }
            ]
        },
        {
            "name": "3.4、压缩性能",
            "con": "无。"
        },
        {
            "name": "3.5、扭转性能",
            "con": "无。"
        },
        {
            "name": "3.6、剪切性能",
            "con": "无。"
        },
        {
            "name": "3.7、拉伸性能",
            "con": "棒材和涡轮盘不同温度的拉伸性能见表3-3。",
            "tableData": [
                {
                    "取样": "棒材 标准热处理",
                    "θ/℃": -196,
                    "σb/MPa": 1750,
                    "σP0.2/MPa": 1160,
                    "δ5/%": 21,
                    "ψ/%": 20
                },
                {
                    "取样": "棒材 标准热处理",
                    "θ/℃": 20,
                    "σb/MPa": 1430,
                    "σP0.2/MPa": 1060,
                    "δ5/%": 22,
                    "ψ/%": 30
                },
                {
                    "取样": "棒材 标准热处理",
                    "θ/℃": 650,
                    "σb/MPa": 1420,
                    "σP0.2/MPa": 1015,
                    "δ5/%": 22,
                    "ψ/%": 22
                },
                {
                    "取样": "棒材 标准热处理",
                    "θ/℃": 700,
                    "σb/MPa": 1275,
                    "σP0.2/MPa": 918,
                    "δ5/%": 20,
                    "ψ/%": 23
                },
                {
                    "取样": "棒材 标准热处理",
                    "θ/℃": 750,
                    "σb/MPa": 1093,
                    "σP0.2/MPa": 895,
                    "δ5/%": 20,
                    "ψ/%": 26
                },
                {
                    "取样": "棒材 标准热处理",
                    "θ/℃": 800,
                    "σb/MPa": 1020,
                    "σP0.2/MPa": 874,
                    "δ5/%": 32,
                    "ψ/%": 43
                },
                {
                    "取样": "棒材 标准热处理",
                    "θ/℃": 850,
                    "σb/MPa": 844,
                    "σP0.2/MPa": 832,
                    "δ5/%": 24,
                    "ψ/%": 63
                },
                {
                    "取样": "棒材 标准热处理",
                    "θ/℃": 900,
                    "σb/MPa": 687,
                    "σP0.2/MPa": 681,
                    "δ5/%": 24,
                    "ψ/%": 44
                },
                {
                    "取样": "涡轮盘弦向 标准热处理",
                    "θ/℃": 20,
                    "σb/MPa": 1455,
                    "σP0.2/MPa": 998,
                    "δ5/%": 19,
                    "ψ/%": 24
                },
                {
                    "取样": "涡轮盘弦向 标准热处理",
                    "θ/℃": 650,
                    "σb/MPa": 1413,
                    "σP0.2/MPa": 935,
                    "δ5/%": 17,
                    "ψ/%": 16
                },
                {
                    "取样": "涡轮盘弦向 标准热处理",
                    "θ/℃": 750,
                    "σb/MPa": 1115,
                    "σP0.2/MPa": 887,
                    "δ5/%": 22,
                    "ψ/%": 21
                },
                {
                    "取样": "涡轮盘弦向 标准热处理",
                    "θ/℃": 800,
                    "σb/MPa": 945,
                    "σP0.2/MPa": 855,
                    "δ5/%": 25,
                    "ψ/%": "-"
                }
            ],
            "tableColumns": [
                {
                    "label": "取样",
                    "prop": "取样"
                },
                {
                    "label": "θ/℃",
                    "prop": "θ/℃"
                },
                {
                    "label": "σb/MPa",
                    "prop": "σb/MPa"
                },
                {
                    "label": "σP0.2/MPa",
                    "prop": "σP0.2/MPa"
                },
                {
                    "label": "δ5/%",
                    "prop": "δ5/%"
                },
                {
                    "label": "ψ/%",
                    "prop": "ψ/%"
                }
            ]
        },
        {
            "name": "3.8、持久性能",
            "con": "圆饼不同温度光滑和缺口持久性能分别见表3-4和表3-5。",
            "tableData": [
                {
                    "取样": "圆饼弦向 标准热处理",
                    "θ/℃": 650,
                    "σ/MPa": 700,
                    "τ/h": ">1845"
                },
                {
                    "取样": "圆饼弦向 标准热处理",
                    "θ/℃": 650,
                    "σ/MPa": 800,
                    "τ/h": 750
                },
                {
                    "取样": "圆饼弦向 标准热处理",
                    "θ/℃": 650,
                    "σ/MPa": 900,
                    "τ/h": 200
                },
                {
                    "取样": "圆饼弦向 标准热处理",
                    "θ/℃": 750,
                    "σ/MPa": 345,
                    "τ/h": 1200
                },
                {
                    "取样": "圆饼弦向 标准热处理",
                    "θ/℃": 750,
                    "σ/MPa": 390,
                    "τ/h": 670
                },
                {
                    "取样": "圆饼弦向 标准热处理",
                    "θ/℃": 750,
                    "σ/MPa": 450,
                    "τ/h": 400
                },
                {
                    "取样": "圆饼弦向 标准热处理",
                    "θ/℃": 750,
                    "σ/MPa": 550,
                    "τ/h": 125
                },
                {
                    "取样": "圆饼弦向 标准热处理",
                    "θ/℃": 750,
                    "σ/MPa": 569,
                    "τ/h": 90
                },
                {
                    "取样": "圆饼弦向标准热处理",
                    "θ/℃": 750,
                    "σ/MPa": 588,
                    "τ/h": 65
                },
                {
                    "取样": "圆饼弦向标准热处理",
                    "θ/℃": 750,
                    "σ/MPa": 620,
                    "τ/h": 46
                },
                {
                    "取样": "圆饼弦向标准热处理",
                    "θ/℃": 800,
                    "σ/MPa": 320,
                    "τ/h": ">208"
                },
                {
                    "取样": "圆饼弦向标准热处理",
                    "θ/℃": 800,
                    "σ/MPa": 350,
                    "τ/h": 175
                },
                {
                    "取样": "圆饼弦向标准热处理",
                    "θ/℃": 800,
                    "σ/MPa": 400,
                    "τ/h": 100
                },
                {
                    "取样": "圆饼弦向标准热处理",
                    "θ/℃": 850,
                    "σ/MPa": 400,
                    "τ/h": 6
                },
                {
                    "取样": "圆饼弦向标准热处理",
                    "θ/℃": 850,
                    "σ/MPa": 530,
                    "τ/h": 3
                },
                {
                    "取样": "圆饼弦向标准热处理",
                    "θ/℃": 850,
                    "σ/MPa": 580,
                    "τ/h": 1
                }
            ],
            "tableColumns": [
                {
                    "label": "取样",
                    "prop": "取样"
                },
                {
                    "label": "θ/℃",
                    "prop": "θ/℃"
                },
                {
                    "label": "σ/MPa",
                    "prop": "σ/MPa"
                },
                {
                    "label": "τ/h",
                    "prop": "τ/h"
                }
            ]
        },
        {
            "name": "3.8_2、表3-5。",
            "con": "",
            "tableData": [
                {
                    "取样": "圆饼，弦向 标准热处理",
                    "θ/℃": 650,
                    "光滑试样_σb/MPa": 843,
                    "光滑试样_τ/h": 301.5,
                    "光滑试样_δ5/%": 26,
                    "光滑试样_ψ/%": 21.4,
                    "缺口试样_τH/h": 884,
                    "τH/τ": 2.9
                },
                {
                    "取样": "圆饼，弦向 标准热处理",
                    "θ/℃": 800,
                    "光滑试样_σb/MPa": 471,
                    "光滑试样_τ/h": 21.83,
                    "光滑试样_δ5/%": 14.8,
                    "光滑试样_ψ/%": 25.7,
                    "缺口试样_τH/h": 121.13,
                    "τH/τ": 5.5
                },
                {
                    "取样": "①缺口半径r=0.2mm。"
                }
            ],
            "tableColumns": [
                {
                    "label": "取样",
                    "prop": "取样"
                },
                {
                    "label": "θ/℃",
                    "prop": "θ/℃"
                },
                {
                    "label": "光滑试样_σb/MPa",
                    "prop": "光滑试样_σb/MPa"
                },
                {
                    "label": "光滑试样_τ/h",
                    "prop": "光滑试样_τ/h"
                },
                {
                    "label": "光滑试样_δ5/%",
                    "prop": "光滑试样_δ5/%"
                },
                {
                    "label": "光滑试样_ψ/%",
                    "prop": "光滑试样_ψ/%"
                },
                {
                    "label": "缺口试样_τH/h",
                    "prop": "缺口试样_τH/h"
                },
                {
                    "label": "τH/τ",
                    "prop": "τH/τ"
                }
            ]
        },
        {
            "name": "3.9、蠕变性能",
            "con": "盘锻件不同温度和应力，100h的蠕变性能见表3-6。",
            "tableData": [
                {
                    "取样": "盘锻件弦向 标准热处理",
                    "θ/℃": 750,
                    "σ/MPa": 460,
                    "100h的蠕变性能_εt/%": 0.508,
                    "100h的蠕变性能_εP/%": 0.172,
                    "100h的蠕变性能_εe/%": 0.336
                },
                {
                    "取样": "盘锻件弦向 标准热处理",
                    "θ/℃": 750,
                    "σ/MPa": 465,
                    "100h的蠕变性能_εt/%": 0.58,
                    "100h的蠕变性能_εP/%": 0.238,
                    "100h的蠕变性能_εe/%": 0.342
                },
                {
                    "取样": "盘锻件弦向 标准热处理",
                    "θ/℃": 750,
                    "σ/MPa": 470,
                    "100h的蠕变性能_εt/%": 0.658,
                    "100h的蠕变性能_εP/%": 0.294,
                    "100h的蠕变性能_εe/%": 0.364
                },
                {
                    "取样": "盘锻件弦向 标准热处理",
                    "θ/℃": 800,
                    "σ/MPa": 157,
                    "100h的蠕变性能_εt/%": 0.137,
                    "100h的蠕变性能_εP/%": 0.047,
                    "100h的蠕变性能_εe/%": 0.09
                },
                {
                    "取样": "盘锻件弦向 标准热处理",
                    "θ/℃": 800,
                    "σ/MPa": 177,
                    "100h的蠕变性能_εt/%": 0.191,
                    "100h的蠕变性能_εP/%": 0.061,
                    "100h的蠕变性能_εe/%": 0.13
                },
                {
                    "取样": "盘锻件弦向 标准热处理",
                    "θ/℃": 800,
                    "σ/MPa": 216,
                    "100h的蠕变性能_εt/%": 0.341,
                    "100h的蠕变性能_εP/%": 0.185,
                    "100h的蠕变性能_εe/%": 0.156
                },
                {
                    "取样": "盘锻件弦向 标准热处理",
                    "θ/℃": 850,
                    "σ/MPa": 98,
                    "100h的蠕变性能_εt/%": 0.102,
                    "100h的蠕变性能_εP/%": 0.027,
                    "100h的蠕变性能_εe/%": 0.075
                },
                {
                    "取样": "盘锻件弦向 标准热处理",
                    "θ/℃": 850,
                    "σ/MPa": 157,
                    "100h的蠕变性能_εt/%": 0.195,
                    "100h的蠕变性能_εP/%": 0.105,
                    "100h的蠕变性能_εe/%": 0.09
                },
                {
                    "取样": "盘锻件弦向 标准热处理",
                    "θ/℃": 850,
                    "σ/MPa": 162,
                    "100h的蠕变性能_εt/%": 0.337,
                    "100h的蠕变性能_εP/%": 0.218,
                    "100h的蠕变性能_εe/%": 0.118
                },
                {
                    "取样": "盘锻件弦向 标准热处理",
                    "θ/℃": 850,
                    "σ/MPa": 177,
                    "100h的蠕变性能_εt/%": 0.386,
                    "100h的蠕变性能_εP/%": 0.257,
                    "100h的蠕变性能_εe/%": 0.128
                }
            ],
            "tableColumns": [
                {
                    "label": "取样",
                    "prop": "取样"
                },
                {
                    "label": "θ/℃",
                    "prop": "θ/℃"
                },
                {
                    "label": "σ/MPa",
                    "prop": "σ/MPa"
                },
                {
                    "label": "100h的蠕变性能_εt/%",
                    "prop": "100h的蠕变性能_εt/%"
                },
                {
                    "label": "100h的蠕变性能_εP/%",
                    "prop": "100h的蠕变性能_εP/%"
                },
                {
                    "label": "100h的蠕变性能_εe/%",
                    "prop": "100h的蠕变性能_εe/%"
                }
            ]
        },
        {
            "name": "3.10、疲劳性能",
            "con": "",
            "two": [
                {
                    "name": "3.10.1、高周疲劳",
                    "con": "盘锻件760℃和800℃，旋转弯曲光滑和缺口疲劳极限见表3-7。",
                    "tableData": [
                        {
                            "取样": "盘锻件，弦向 标准热处理",
                            "θ/℃": 760,
                            "Nf=10^7周，旋转弯曲光滑疲劳_σ-1/MPa": 490,
                            "Nf=10^7周，旋转弯曲缺口(Kt=1.89)疲劳_σ-1H/MPa": 353
                        },
                        {
                            "取样": "盘锻件，弦向 标准热处理",
                            "θ/℃": 800,
                            "Nf=10^7周，旋转弯曲光滑疲劳_σ-1/MPa": 430,
                            "Nf=10^7周，旋转弯曲缺口(Kt=1.89)疲劳_σ-1H/MPa": 314
                        }
                    ],
                    "tableColumns": [
                        {
                            "label": "取样",
                            "prop": "取样"
                        },
                        {
                            "label": "θ/℃",
                            "prop": "θ/℃"
                        },
                        {
                            "label": "Nf=10^7周，旋转弯曲光滑疲劳_σ-1/MPa",
                            "prop": "Nf=10^7周，旋转弯曲光滑疲劳_σ-1/MPa"
                        },
                        {
                            "label": "Nf=10^7周，旋转弯曲缺口(Kt=1.89)疲劳_σ-1H/MPa",
                            "prop": "Nf=10^7周，旋转弯曲缺口(Kt=1.89)疲劳_σ-1H/MPa"
                        }
                    ]
                },
                {
                    "name": "3.10.2、低周疲劳",
                    "con": "",
                    "third": [
                        {
                            "name": "3.10.2.1、圆饼750℃的低周疲劳性能见表3-8。",
                            "con": "",
                            "tableData": [
                                {
                                    "取样": "圆饼弦向",
                                    "热处理": "标准热处理",
                                    "θ/℃": 750,
                                    "稳态迟滞回线特征值_Δεt/2/%": 0.797,
                                    "稳态迟滞回线特征值_Δεe/2/%": 0.492,
                                    "稳态迟滞回线特征值_ΔεP/2/%": 0.305,
                                    "稳态迟滞回线特征值_Δσ/2/%": 890,
                                    "2Nf/反向数": 624
                                },
                                {
                                    "取样": "圆饼弦向",
                                    "热处理": "标准热处理",
                                    "θ/℃": 750,
                                    "稳态迟滞回线特征值_Δεt/2/%": 0.598,
                                    "稳态迟滞回线特征值_Δεe/2/%": 0.434,
                                    "稳态迟滞回线特征值_ΔεP/2/%": 0.164,
                                    "稳态迟滞回线特征值_Δσ/2/%": 785,
                                    "2Nf/反向数": 2104
                                },
                                {
                                    "取样": "圆饼弦向",
                                    "热处理": "标准热处理",
                                    "θ/℃": 750,
                                    "稳态迟滞回线特征值_Δεt/2/%": 0.499,
                                    "稳态迟滞回线特征值_Δεe/2/%": 0.363,
                                    "稳态迟滞回线特征值_ΔεP/2/%": 0.136,
                                    "稳态迟滞回线特征值_Δσ/2/%": 657,
                                    "2Nf/反向数": 5024
                                },
                                {
                                    "取样": "圆饼弦向",
                                    "热处理": "标准热处理",
                                    "θ/℃": 750,
                                    "稳态迟滞回线特征值_Δεt/2/%": 0.399,
                                    "稳态迟滞回线特征值_Δεe/2/%": 0.362,
                                    "稳态迟滞回线特征值_ΔεP/2/%": 0.037,
                                    "稳态迟滞回线特征值_Δσ/2/%": 655,
                                    "2Nf/反向数": 15050
                                },
                                {
                                    "取样": "圆饼弦向",
                                    "热处理": "标准热处理",
                                    "θ/℃": 750,
                                    "稳态迟滞回线特征值_Δεt/2/%": 0.369,
                                    "稳态迟滞回线特征值_Δεe/2/%": 0.339,
                                    "稳态迟滞回线特征值_ΔεP/2/%": 0.03,
                                    "稳态迟滞回线特征值_Δσ/2/%": 614,
                                    "2Nf/反向数": 20794
                                },
                                {
                                    "取样": "圆饼弦向",
                                    "热处理": "标准热处理",
                                    "θ/℃": 750,
                                    "稳态迟滞回线特征值_Δεt/2/%": 0.3,
                                    "稳态迟滞回线特征值_Δεe/2/%": 0.282,
                                    "稳态迟滞回线特征值_ΔεP/2/%": 0.018,
                                    "稳态迟滞回线特征值_Δσ/2/%": 510,
                                    "2Nf/反向数": 101898
                                },
                                {
                                    "取样": "应变疲劳参量",
                                    "热处理": "σ'f/MPa",
                                    "θ/℃": "b",
                                    "稳态迟滞回线特征值_Δεt/2/%": "ε'f/%",
                                    "稳态迟滞回线特征值_Δεe/2/%": "c",
                                    "稳态迟滞回线特征值_ΔεP/2/%": "K'/MPa",
                                    "稳态迟滞回线特征值_Δσ/2/%": "n'"
                                },
                                {
                                    "取样": "应变疲劳参量",
                                    "热处理": 1734,
                                    "θ/℃": -0.106,
                                    "稳态迟滞回线特征值_Δεt/2/%": 16.6,
                                    "稳态迟滞回线特征值_Δεe/2/%": -0.608,
                                    "稳态迟滞回线特征值_ΔεP/2/%": 2123,
                                    "稳态迟滞回线特征值_Δσ/2/%": 0.158
                                },
                                {
                                    "取样": "应变-寿命曲线方程",
                                    "热处理": "Δεt/2=0.0096（2Nf）^（-0.106）+0.166（2Nf）^（-0.608）"
                                },
                                {
                                    "取样": "循环应力-应变曲线方程",
                                    "热处理": "Δεt/2=Δσ/362000+(Δσ/4246)^6.33"
                                },
                                {
                                    "取样": "试验条件",
                                    "热处理": "d6.0mm试样；轴向应变；Rε=—1;三角波；f=(0.05～1.0)Hz;失效判据：断裂"
                                }
                            ],
                            "tableColumns": [
                                {
                                    "label": "取样",
                                    "prop": "取样"
                                },
                                {
                                    "label": "热处理",
                                    "prop": "热处理"
                                },
                                {
                                    "label": "θ/℃",
                                    "prop": "θ/℃"
                                },
                                {
                                    "label": "稳态迟滞回线特征值_Δεt/2/%",
                                    "prop": "稳态迟滞回线特征值_Δεt/2/%"
                                },
                                {
                                    "label": "稳态迟滞回线特征值_Δεe/2/%",
                                    "prop": "稳态迟滞回线特征值_Δεe/2/%"
                                },
                                {
                                    "label": "稳态迟滞回线特征值_ΔεP/2/%",
                                    "prop": "稳态迟滞回线特征值_ΔεP/2/%"
                                },
                                {
                                    "label": "稳态迟滞回线特征值_Δσ/2/%",
                                    "prop": "稳态迟滞回线特征值_Δσ/2/%"
                                },
                                {
                                    "label": "2Nf/反向数",
                                    "prop": "2Nf/反向数"
                                }
                            ]
                        },
                        {
                            "name": "3.10.2.2、圆饼750℃的低周疲劳ε-N曲线见图3-1。",
                            "con": "",
                            "xAxisData": [],
                            "echartMsg": {
                                "echartId": "31022",
                                "xName": "",
                                "yName": "",
                                "minX": 701.0983,
                                "minY": 0.0003
                            },
                            "seriesData": [
                                {
                                    "name": "Δεt/2-2Nf",
                                    "type": "line",
                                    "smooth": "smooth",
                                    "data": [
                                        [
                                            "711.7484",
                                            "0.0091"
                                        ],
                                        [
                                            "2256.9083",
                                            "0.0080"
                                        ],
                                        [
                                            "5200.0999",
                                            "0.0071"
                                        ],
                                        [
                                            "16571.6604",
                                            "0.0064"
                                        ],
                                        [
                                            "21797.8125",
                                            "0.0062"
                                        ],
                                        [
                                            "104129.8885",
                                            "0.0053"
                                        ]
                                    ]
                                },
                                {
                                    "name": "Δεe/2-2Nf",
                                    "type": "line",
                                    "smooth": "smooth",
                                    "data": [
                                        [
                                            "722.5603",
                                            "0.0069"
                                        ],
                                        [
                                            "2256.9083",
                                            "0.0067"
                                        ],
                                        [
                                            "5122.2893",
                                            "0.0060"
                                        ],
                                        [
                                            "16571.6604",
                                            "0.0057"
                                        ],
                                        [
                                            "23861.5354",
                                            "0.0056"
                                        ],
                                        [
                                            "105711.6818",
                                            "0.0048"
                                        ]
                                    ]
                                },
                                {
                                    "name": "ΔεP/2-2Nf",
                                    "type": "line",
                                    "smooth": "smooth",
                                    "data": [
                                        [
                                            "701.0983",
                                            "0.0054"
                                        ],
                                        [
                                            "2189.8721",
                                            "0.0025"
                                        ],
                                        [
                                            "5045.6431",
                                            "0.0020"
                                        ],
                                        [
                                            "16823.3936",
                                            "0.0006"
                                        ],
                                        [
                                            "22806.3429",
                                            "0.0005"
                                        ],
                                        [
                                            "101036.9542",
                                            "0.0003"
                                        ]
                                    ]
                                }
                            ]
                        }
                    ]
                },
                {
                    "name": "3.10.3、特种疲劳",
                    "con": "无。"
                }
            ]
        },
        {
            "name": "3.11、裂纹扩展速率",
            "con": "圆饼不同温度，应力比为0.05的疲劳裂纹da/dN-ΔK曲线见图3-2。",
            "xAxisData": [],
            "echartMsg": {
                "echartId": "311",
                "xName": "",
                "yName": "",
                "minX": 20.0763,
                "minY": 0
            },
            "seriesData": [
                {
                    "name": "850℃-ΔK",
                    "type": "line",
                    "smooth": "smooth",
                    "data": [
                        [
                            "21.5267",
                            "0.0000"
                        ],
                        [
                            "21.1450",
                            "0.0000"
                        ],
                        [
                            "20.7634",
                            "0.0000"
                        ],
                        [
                            "24.3512",
                            "0.0000"
                        ],
                        [
                            "23.9695",
                            "0.0000"
                        ],
                        [
                            "23.4351",
                            "0.0000"
                        ],
                        [
                            "22.8244",
                            "0.0000"
                        ],
                        [
                            "25.8015",
                            "0.0000"
                        ],
                        [
                            "25.4199",
                            "0.0000"
                        ],
                        [
                            "25.4199",
                            "0.0000"
                        ],
                        [
                            "25.0382",
                            "0.0000"
                        ],
                        [
                            "24.6565",
                            "0.0000"
                        ],
                        [
                            "40.2409",
                            "0.0000"
                        ],
                        [
                            "41.0690",
                            "0.0000"
                        ],
                        [
                            "41.7197",
                            "0.0000"
                        ],
                        [
                            "42.5478",
                            "0.0000"
                        ],
                        [
                            "43.3612",
                            "0.0000"
                        ],
                        [
                            "44.8400",
                            "0.0000"
                        ],
                        [
                            "45.0027",
                            "0.0000"
                        ]
                    ]
                },
                {
                    "name": "800℃-ΔK",
                    "type": "line",
                    "smooth": "smooth",
                    "data": [
                        [
                            "22.4784",
                            "0.0000"
                        ],
                        [
                            "24.6986",
                            "0.0000"
                        ],
                        [
                            "22.4428",
                            "0.0000"
                        ],
                        [
                            "21.9847",
                            "0.0000"
                        ],
                        [
                            "21.4504",
                            "0.0000"
                        ],
                        [
                            "20.9924",
                            "0.0000"
                        ],
                        [
                            "20.7634",
                            "0.0000"
                        ],
                        [
                            "20.3053",
                            "0.0000"
                        ],
                        [
                            "26.1832",
                            "0.0000"
                        ],
                        [
                            "25.7252",
                            "0.0000"
                        ],
                        [
                            "25.0382",
                            "0.0000"
                        ],
                        [
                            "23.8168",
                            "0.0000"
                        ],
                        [
                            "29.7710",
                            "0.0000"
                        ],
                        [
                            "29.0840",
                            "0.0000"
                        ],
                        [
                            "28.3970",
                            "0.0000"
                        ],
                        [
                            "27.7099",
                            "0.0000"
                        ],
                        [
                            "28.0729",
                            "0.0000"
                        ],
                        [
                            "27.0951",
                            "0.0000"
                        ],
                        [
                            "30.5312",
                            "0.0000"
                        ],
                        [
                            "30.8998",
                            "0.0000"
                        ],
                        [
                            "31.2684",
                            "0.0000"
                        ],
                        [
                            "31.7711",
                            "0.0000"
                        ],
                        [
                            "32.1397",
                            "0.0000"
                        ],
                        [
                            "32.5083",
                            "0.0000"
                        ],
                        [
                            "33.1338",
                            "0.0000"
                        ],
                        [
                            "33.5024",
                            "0.0000"
                        ],
                        [
                            "34.2396",
                            "0.0000"
                        ],
                        [
                            "34.3736",
                            "0.0000"
                        ],
                        [
                            "34.6194",
                            "0.0000"
                        ],
                        [
                            "34.9880",
                            "0.0000"
                        ],
                        [
                            "35.8592",
                            "0.0000"
                        ],
                        [
                            "36.7193",
                            "0.0000"
                        ],
                        [
                            "37.2108",
                            "0.0000"
                        ],
                        [
                            "37.3336",
                            "0.0000"
                        ],
                        [
                            "38.2049",
                            "0.0000"
                        ],
                        [
                            "38.2049",
                            "0.0000"
                        ],
                        [
                            "38.9533",
                            "0.0000"
                        ],
                        [
                            "40.9064",
                            "0.0000"
                        ],
                        [
                            "42.0450",
                            "0.0000"
                        ],
                        [
                            "43.3612",
                            "0.0000"
                        ],
                        [
                            "44.8400",
                            "0.0000"
                        ],
                        [
                            "46.6442",
                            "0.0000"
                        ],
                        [
                            "48.9363",
                            "0.0000"
                        ]
                    ]
                },
                {
                    "name": "750℃-ΔK",
                    "type": "line",
                    "smooth": "smooth",
                    "data": [
                        [
                            "22.7481",
                            "0.0000"
                        ],
                        [
                            "22.1374",
                            "0.0000"
                        ],
                        [
                            "21.5267",
                            "0.0000"
                        ],
                        [
                            "20.9160",
                            "0.0000"
                        ],
                        [
                            "20.5343",
                            "0.0000"
                        ],
                        [
                            "20.3053",
                            "0.0000"
                        ],
                        [
                            "20.0763",
                            "0.0000"
                        ],
                        [
                            "20.0763",
                            "-0.0000"
                        ],
                        [
                            "20.0763",
                            "-0.0000"
                        ],
                        [
                            "20.0763",
                            "-0.0000"
                        ],
                        [
                            "20.0763",
                            "-0.0000"
                        ],
                        [
                            "26.7939",
                            "0.0000"
                        ],
                        [
                            "26.0305",
                            "0.0000"
                        ],
                        [
                            "25.4962",
                            "0.0000"
                        ],
                        [
                            "24.8092",
                            "0.0000"
                        ],
                        [
                            "24.0458",
                            "0.0000"
                        ],
                        [
                            "27.6240",
                            "0.0000"
                        ],
                        [
                            "27.8084",
                            "0.0000"
                        ],
                        [
                            "28.5137",
                            "0.0000"
                        ],
                        [
                            "28.7862",
                            "0.0000"
                        ],
                        [
                            "29.1389",
                            "0.0000"
                        ],
                        [
                            "29.5797",
                            "0.0000"
                        ],
                        [
                            "30.5312",
                            "0.0000"
                        ],
                        [
                            "30.8998",
                            "0.0000"
                        ],
                        [
                            "31.2684",
                            "0.0000"
                        ],
                        [
                            "32.5083",
                            "0.0000"
                        ],
                        [
                            "32.8881",
                            "0.0000"
                        ],
                        [
                            "33.7481",
                            "0.0000"
                        ],
                        [
                            "34.2396",
                            "0.0000"
                        ],
                        [
                            "34.9880",
                            "0.0000"
                        ],
                        [
                            "35.2337",
                            "0.0000"
                        ],
                        [
                            "36.4736",
                            "0.0000"
                        ],
                        [
                            "37.7134",
                            "0.0000"
                        ],
                        [
                            "38.3278",
                            "0.0000"
                        ],
                        [
                            "39.0761",
                            "0.0000"
                        ],
                        [
                            "39.5676",
                            "0.0000"
                        ],
                        [
                            "40.7437",
                            "0.0000"
                        ],
                        [
                            "41.2317",
                            "0.0000"
                        ],
                        [
                            "42.3704",
                            "0.0000"
                        ],
                        [
                            "44.1745",
                            "0.0000"
                        ],
                        [
                            "45.8160",
                            "0.0000"
                        ],
                        [
                            "47.2948",
                            "0.0000"
                        ]
                    ]
                },
                {
                    "name": "650℃-ΔK",
                    "type": "line",
                    "smooth": "smooth",
                    "data": [
                        [
                            "27.4046",
                            "0.0000"
                        ],
                        [
                            "26.7939",
                            "0.0000"
                        ],
                        [
                            "26.0305",
                            "0.0000"
                        ],
                        [
                            "25.4962",
                            "0.0000"
                        ],
                        [
                            "24.8855",
                            "0.0000"
                        ],
                        [
                            "24.3512",
                            "0.0000"
                        ],
                        [
                            "23.5878",
                            "0.0000"
                        ],
                        [
                            "22.8244",
                            "0.0000"
                        ],
                        [
                            "23.1298",
                            "0.0000"
                        ],
                        [
                            "22.3664",
                            "0.0000"
                        ],
                        [
                            "21.9084",
                            "0.0000"
                        ],
                        [
                            "21.1450",
                            "0.0000"
                        ],
                        [
                            "31.7557",
                            "0.0000"
                        ],
                        [
                            "28.1610",
                            "0.0000"
                        ],
                        [
                            "28.8744",
                            "0.0000"
                        ],
                        [
                            "29.4915",
                            "0.0000"
                        ],
                        [
                            "29.6679",
                            "0.0000"
                        ],
                        [
                            "36.7021",
                            "0.0000"
                        ],
                        [
                            "30.4084",
                            "0.0000"
                        ],
                        [
                            "31.4025",
                            "0.0000"
                        ],
                        [
                            "31.5253",
                            "0.0000"
                        ],
                        [
                            "32.1397",
                            "0.0000"
                        ],
                        [
                            "32.6311",
                            "0.0000"
                        ],
                        [
                            "33.2567",
                            "0.0000"
                        ],
                        [
                            "33.9939",
                            "0.0000"
                        ],
                        [
                            "34.2396",
                            "0.0000"
                        ],
                        [
                            "34.8651",
                            "0.0000"
                        ],
                        [
                            "36.3507",
                            "0.0000"
                        ],
                        [
                            "37.5905",
                            "0.0000"
                        ],
                        [
                            "39.5676",
                            "0.0000"
                        ],
                        [
                            "38.4506",
                            "0.0000"
                        ],
                        [
                            "40.7437",
                            "0.0000"
                        ],
                        [
                            "42.0450",
                            "0.0000"
                        ],
                        [
                            "43.5239",
                            "0.0000"
                        ],
                        [
                            "45.1653",
                            "0.0000"
                        ],
                        [
                            "49.5870",
                            "0.0000"
                        ]
                    ]
                },
                {
                    "name": "20℃-ΔK",
                    "type": "line",
                    "smooth": "smooth",
                    "data": [
                        [
                            "20.6991",
                            "0.0000"
                        ],
                        [
                            "20.9636",
                            "0.0000"
                        ],
                        [
                            "21.2361",
                            "0.0000"
                        ],
                        [
                            "21.3243",
                            "0.0000"
                        ],
                        [
                            "21.5006",
                            "0.0000"
                        ],
                        [
                            "21.5888",
                            "0.0000"
                        ],
                        [
                            "21.8532",
                            "0.0000"
                        ],
                        [
                            "22.0296",
                            "0.0000"
                        ],
                        [
                            "22.3021",
                            "0.0000"
                        ],
                        [
                            "22.9193",
                            "0.0000"
                        ],
                        [
                            "23.3681",
                            "0.0000"
                        ],
                        [
                            "24.4341",
                            "0.0000"
                        ],
                        [
                            "25.5882",
                            "0.0000"
                        ],
                        [
                            "26.3817",
                            "0.0000"
                        ],
                        [
                            "26.7424",
                            "0.0000"
                        ],
                        [
                            "27.5359",
                            "0.0000"
                        ],
                        [
                            "28.8744",
                            "0.0000"
                        ],
                        [
                            "31.0227",
                            "0.0000"
                        ],
                        [
                            "33.5024",
                            "0.0000"
                        ],
                        [
                            "34.8651",
                            "0.0000"
                        ],
                        [
                            "36.2278",
                            "0.0000"
                        ],
                        [
                            "36.4736",
                            "0.0000"
                        ],
                        [
                            "37.9592",
                            "0.0000"
                        ],
                        [
                            "39.8133",
                            "0.0000"
                        ],
                        [
                            "42.5478",
                            "0.0000"
                        ],
                        [
                            "43.3612",
                            "0.0000"
                        ],
                        [
                            "44.5147",
                            "0.0000"
                        ],
                        [
                            "45.1653",
                            "0.0000"
                        ],
                        [
                            "46.6442",
                            "0.0000"
                        ],
                        [
                            "48.7737",
                            "0.0000"
                        ],
                        [
                            "49.5870",
                            "0.0000"
                        ],
                        [
                            "50.0750",
                            "0.0000"
                        ],
                        [
                            "51.2285",
                            "0.0000"
                        ],
                        [
                            "52.2045",
                            "0.0000"
                        ]
                    ]
                }
            ]
        },
        {
            "name": "3.12、断裂韧度",
            "con": "盘锻件经750℃长期时效，不同时效时间的室温断裂韧性曲线见图3-3。",
            "xAxisData": [],
            "echartMsg": {
                "echartId": "312",
                "xName": "",
                "yName": "",
                "minX": -1.5955,
                "minY": 23.0109
            },
            "seriesData": [
                {
                    "name": "时效时间",
                    "type": "line",
                    "smooth": "smooth",
                    "data": [
                        [
                            "-1.5955",
                            "79.3903"
                        ],
                        [
                            "99.7400",
                            "55.0277"
                        ],
                        [
                            "198.6685",
                            "41.6682"
                        ],
                        [
                            "505.8043",
                            "32.0472"
                        ],
                        [
                            "1002.3725",
                            "23.0109"
                        ]
                    ]
                }
            ]
        },
        {
            "name": "3.13、松弛性能",
            "con": "无。"
        }
    ],
    "craft": [
        {
            "name": "4.1、成形工艺与性能",
            "con": "表4-1",
            "tableData": [
                {
                    "加工类型": "钢锭开坯",
                    "加热温度": "1160℃±10℃",
                    "开锻/终锻温度": "开锻>1050℃;终锻≥980℃",
                    "变形量": "最后一火变形量不小于30%"
                },
                {
                    "加工类型": "镦饼",
                    "加热温度": "1150℃±10℃",
                    "开锻/终锻温度": "开锻>1050℃;终锻≥980℃",
                    "变形量": "一火成形"
                },
                {
                    "加工类型": "模锻",
                    "加热温度": "1150℃±10℃",
                    "开锻/终锻温度": "开锻>1050℃;终锻≥980℃",
                    "变形量": "一火成形"
                }
            ],
            "tableColumns": [
                {
                    "label": "加工类型",
                    "prop": "加工类型"
                },
                {
                    "label": "加热温度",
                    "prop": "加热温度"
                },
                {
                    "label": "开锻/终锻温度",
                    "prop": "开锻/终锻温度"
                },
                {
                    "label": "变形量",
                    "prop": "变形量"
                }
            ]
        },
        {
            "name": "4.2、工艺性能",
            "con": "无。"
        },
        {
            "name": "4.3、焊接性能",
            "con": "采用Ni-Cr-Si-Cu-Mo-Co钎料钎焊GH4586与1Cr18Ni9Ti或GH4141合金，可以得到满意的室温和高温的接头抗拉强度。"
        },
        {
            "name": "4.4、零件热处理工艺",
            "con": "同各品种的标准热处理制度。"
        },
        {
            "name": "4.5、表面处理工艺",
            "con": "无。"
        },
        {
            "name": "4.6、切削加工与磨削性能",
            "con": "合金具有良好的切削加工性能。"
        }
    ],
    "microstructures": [
        {
            "name": "5.1、相变温度",
            "con": "M23C6型碳化物析出峰值为800℃。"
        },
        {
            "name": "5.2、时间-温度-组织转变曲线",
            "con": "合金固溶温度与碳化物数量的关系见图5-1，时效温度与碳化物数量关系见图5-2。",
            "xAxisData": [],
            "echartMsg": {
                "echartId": "52",
                "xName": "",
                "yName": "",
                "minX": 1000.5994,
                "minY": 0.0709
            },
            "seriesData": [
                {
                    "name": "MC-固溶温度",
                    "type": "line",
                    "smooth": "smooth",
                    "data": [
                        [
                            "1003.4026",
                            "0.0896"
                        ],
                        [
                            "1041.6964",
                            "0.1081"
                        ],
                        [
                            "1067.2256",
                            "0.1192"
                        ],
                        [
                            "1082.2428",
                            "0.1155"
                        ],
                        [
                            "1101.6650",
                            "0.1265"
                        ],
                        [
                            "1141.6608",
                            "0.1155"
                        ],
                        [
                            "1199.3768",
                            "0.0709"
                        ]
                    ]
                },
                {
                    "name": "M6C-固溶温度",
                    "type": "line",
                    "smooth": "smooth",
                    "data": [
                        [
                            "1000.5994",
                            "0.1637"
                        ],
                        [
                            "1041.6964",
                            "0.8554"
                        ],
                        [
                            "1070.0288",
                            "0.8775"
                        ],
                        [
                            "1081.1415",
                            "1.0485"
                        ],
                        [
                            "1100.5637",
                            "0.2419"
                        ],
                        [
                            "1141.1101",
                            "0.1862"
                        ]
                    ]
                }
            ]
        },
        {
            "name": "5.2_2、图5-2",
            "con": "",
            "xAxisData": [],
            "echartMsg": {
                "echartId": "52_2",
                "xName": "",
                "yName": "",
                "minX": 604.8568,
                "minY": 0.084
            },
            "seriesData": [
                {
                    "name": "MC-时效温度",
                    "type": "line",
                    "smooth": "smooth",
                    "data": [
                        [
                            "604.8568",
                            "0.0840"
                        ],
                        [
                            "736.9802",
                            "0.1255"
                        ],
                        [
                            "765.5532",
                            "0.1158"
                        ],
                        [
                            "847.6201",
                            "0.1134"
                        ],
                        [
                            "897.6766",
                            "0.1328"
                        ],
                        [
                            "949.9888",
                            "0.1376"
                        ],
                        [
                            "1001.2269",
                            "0.1376"
                        ]
                    ]
                },
                {
                    "name": "M6C-时效温度",
                    "type": "line",
                    "smooth": "smooth",
                    "data": [
                        [
                            "740.5250",
                            "0.1109"
                        ],
                        [
                            "759.5379",
                            "0.1768"
                        ],
                        [
                            "852.4539",
                            "0.1962"
                        ],
                        [
                            "903.5846",
                            "0.2354"
                        ],
                        [
                            "948.8073",
                            "0.2817"
                        ],
                        [
                            "998.8638",
                            "0.8119"
                        ]
                    ]
                },
                {
                    "name": "M23C6-时效温度",
                    "type": "line",
                    "smooth": "smooth",
                    "data": [
                        [
                            "741.7066",
                            "0.1768"
                        ],
                        [
                            "757.1747",
                            "0.2255"
                        ],
                        [
                            "851.1649",
                            "0.4968"
                        ],
                        [
                            "896.4950",
                            "0.4088"
                        ],
                        [
                            "947.6257",
                            "0.4503"
                        ]
                    ]
                }
            ]
        },
        {
            "name": "5.3、典型组织",
            "con": "合金经标准热处理后的组织由γ基体、γ'相，MC和M23C6型碳化物组成。其中γ'相是主要强化相，ω(γ')约占合金的23%~25%；MC主要是合金凝固时由液态析出的TiC，以大颗粒状分布在晶内；M23C6主要分布在晶界上：M6C分布在晶内和晶界上，900℃以上时效时大量析出，ω(M6C)约占合金的1.0%~1.3%，是合金重要强化相之一。@@合金经固溶和标准热处理后的组织和析出相形貌分别见图5-3和图5-4。"
        }
    ]
}